Guia_TP/CLP_CESE/CLP_CESE.srcs/sources_1/new/adder_1_bit.vhd
----------------------------------------------------------------------------------
-- Company: 
-- Engineer: 
-- 
-- Create Date: 27.08.2026 19:23:36
-- Design Name: 
-- Module Name: adder_1_bit - Behavioral
-- Project Name: 
-- Target Devices: 
-- Tool Versions: 
-- Description: Sumador completo de 1 bit con acarreo de entrada y salida.
-- 
-- Dependencies: 
-- 
-- Revision:
-- Revision 0.01 - File Created
-- Additional Comments:
-- 
----------------------------------------------------------------------------------


library IEEE;
use IEEE.STD_LOGIC_1164.ALL;

-- Uncomment the following library declaration if using
-- arithmetic functions with Signed or Unsigned values
--use IEEE.NUMERIC_STD.ALL;

-- Uncomment the following library declaration if instantiating
-- any Xilinx leaf cells in this code.
--library UNISIM;
--use UNISIM.VComponents.all;

entity adder_1_bit is
    Port ( ci : in STD_LOGIC;
           a : in STD_LOGIC;
           b : in STD_LOGIC;
           s : out STD_LOGIC;
           co : out STD_LOGIC);
end adder_1_bit;

architecture Behavioral of adder_1_bit is

begin
    
    s<= a xor b xor ci;
    co<= (a and b) or (b and ci) or (a and ci);

end Behavioral;

Guia_TP/cocotb/waveforms/adder_1_bit.vcd
$date
  Sun Aug 30 19:24:37 2026
$end
$version
  GHDL v0
$end
$timescale
  1 ps
$end
$scope module standard $end
$upscope $end
$scope module textio $end
$upscope $end
$scope module std_logic_1164 $end
$upscope $end
$scope module adder_1_bit $end
$var reg 1 ! ci $end
$var reg 1 " a $end
$var reg 1 # b $end
$var reg 1 $ s $end
$var reg 1 % co $end
$upscope $end
$enddefinitions $end
#0
0!
0"
0#
0$
0%
#10000
1!
1$
#20000
0!
1#
#30000
1!
0$
1%
#40000
0!
1"
0#
1$
0%
#50000
1!
0$
1%
#60000
0!
1#
#70000
1!
1$
