Guia_TP/CLP_CESE/CLP_CESE.srcs/sources_1/new/adder_1_bit.vhd
----------------------------------------------------------------------------------
-- Company: 
-- Engineer: 
-- 
-- Create Date: 27.08.2026 19:23:36
-- Design Name: 
-- Module Name: adder_1_bit - Behavioral
-- Project Name: 
-- Target Devices: 
-- Tool Versions: 
-- Description: Sumador completo de 1 bit con acarreo de entrada y salida.
-- 
-- Dependencies: 
-- 
-- Revision:
-- Revision 0.01 - File Created
-- Additional Comments:
-- 
----------------------------------------------------------------------------------


library IEEE;
use IEEE.STD_LOGIC_1164.ALL;

-- Uncomment the following library declaration if using
-- arithmetic functions with Signed or Unsigned values
--use IEEE.NUMERIC_STD.ALL;

-- Uncomment the following library declaration if instantiating
-- any Xilinx leaf cells in this code.
--library UNISIM;
--use UNISIM.VComponents.all;

entity adder_1_bit is
    Port ( ci : in STD_LOGIC;
           a : in STD_LOGIC;
           b : in STD_LOGIC;
           s : out STD_LOGIC;
           co : out STD_LOGIC);
end adder_1_bit;

architecture Behavioral of adder_1_bit is

begin
    
    s<= a xor b xor ci;
    co<= (a and b) or (b and ci) or (a and ci);

end Behavioral;

Guia_TP/CLP_CESE/CLP_CESE.srcs/sources_1/new/adder_4_bits.vhd
----------------------------------------------------------------------------------
-- Company: 
-- Engineer: 
-- 
-- Create Date: 27.08.2026 19:49:11
-- Design Name: 
-- Module Name: adder_4_bits - Behavioral
-- Project Name: 
-- Target Devices: 
-- Tool Versions: 
-- Description: Sumador estructural de 4 bits formado por cuatro sumadores completos.
-- 
-- Dependencies: 
-- 
-- Revision:
-- Revision 0.01 - File Created
-- Additional Comments:
-- 
----------------------------------------------------------------------------------


library IEEE;
use IEEE.STD_LOGIC_1164.ALL;

library work;
use work.adder_1_bit;
-- Uncomment the following library declaration if using
-- arithmetic functions with Signed or Unsigned values
--use IEEE.NUMERIC_STD.ALL;

-- Uncomment the following library declaration if instantiating
-- any Xilinx leaf cells in this code.
--library UNISIM;
--use UNISIM.VComponents.all;

entity adder_4_bits is
    Port ( ci : in STD_LOGIC;
            a : in STD_LOGIC_VECTOR(4-1 downto 0);
            b : in STD_LOGIC_VECTOR(4-1 downto 0);
            s : out STD_LOGIC_VECTOR(4-1 downto 0);
           co : out STD_LOGIC);
end adder_4_bits;

architecture Behavioral of adder_4_bits is
    signal c_vector : STD_LOGIC_VECTOR(5-1 downto 0);
begin
    c_vector(0) <= ci;
    co <= c_vector(4);

    ciclo : for i in 0 to 3 generate
        adder_1_bit_instance : entity work.adder_1_bit
            port map (
                ci => c_vector(i),
                a  => a(i),
                b  => b(i),
                s  => s(i),
                co => c_vector(i + 1)
            );
    end generate ciclo;
end Behavioral;

Guia_TP/cocotb/waveforms/adder_4_bits.vcd
$date
  Sun Aug 30 19:24:43 2026
$end
$version
  GHDL v0
$end
$timescale
  1 ps
$end
$scope module standard $end
$upscope $end
$scope module textio $end
$upscope $end
$scope module std_logic_1164 $end
$upscope $end
$scope module adder_4_bits $end
$var reg 1 ! ci $end
$var reg 4 " a[3:0] $end
$var reg 4 # b[3:0] $end
$var reg 4 $ s[3:0] $end
$var reg 1 % co $end
$var reg 5 & c_vector[4:0] $end
$scope module ciclo(0) $end
$scope module adder_1_bit_instance $end
$var reg 1 ' ci $end
$var reg 1 ( a $end
$var reg 1 ) b $end
$var reg 1 * s $end
$var reg 1 + co $end
$upscope $end
$upscope $end
$scope module ciclo(1) $end
$scope module adder_1_bit_instance $end
$var reg 1 , ci $end
$var reg 1 - a $end
$var reg 1 . b $end
$var reg 1 / s $end
$var reg 1 0 co $end
$upscope $end
$upscope $end
$scope module ciclo(2) $end
$scope module adder_1_bit_instance $end
$var reg 1 1 ci $end
$var reg 1 2 a $end
$var reg 1 3 b $end
$var reg 1 4 s $end
$var reg 1 5 co $end
$upscope $end
$upscope $end
$scope module ciclo(3) $end
$scope module adder_1_bit_instance $end
$var reg 1 6 ci $end
$var reg 1 7 a $end
$var reg 1 8 b $end
$var reg 1 9 s $end
$var reg 1 : co $end
$upscope $end
$upscope $end
$upscope $end
$enddefinitions $end
#0
0!
b0000 "
b0000 #
b0000 $
0%
b00000 &
0'
0(
0)
0*
0+
0,
0-
0.
0/
00
01
02
03
04
05
06
07
08
09
0:
#10000
b0001 "
b0001 #
b0010 $
b00010 &
1(
1)
1+
1,
1/
#20000
b0101 "
b0011 #
b1000 $
b01110 &
1.
0/
10
11
12
04
15
16
19
#30000
1!
b1001 $
b01111 &
1'
1*
#40000
0!
b0111 "
b0001 #
b1000 $
b01110 &
0'
0*
1-
0.
#50000
1!
b1111 "
b0000 #
b0000 $
1%
b11111 &
1'
0)
0*
1+
1,
0/
10
11
04
15
16
17
09
1:
#60000
0!
b1001 "
b1001 #
b0010 $
b10010 &
0'
1)
0*
0-
1/
00
01
02
04
05
06
18
09
#70000
1!
b1111 "
b1111 #
b1111 $
b11111 &
1'
1*
1-
1.
10
11
12
13
14
15
16
19
