Guia_TP/CLP_CESE/CLP_CESE.srcs/sources_1/new/mux_2_a_1.vhd
----------------------------------------------------------------------------------
-- Company: 
-- Engineer: 
-- 
-- Create Date: 27.08.2026 20:36:34
-- Design Name: 
-- Module Name: mux_2_a_1 - Behavioral
-- Project Name: 
-- Target Devices: 
-- Tool Versions: 
-- Description: Multiplexor combinacional de dos entradas de 1 bit.
-- 
-- Dependencies: 
-- 
-- Revision:
-- Revision 0.01 - File Created
-- Additional Comments:
-- 
----------------------------------------------------------------------------------


library IEEE;
use IEEE.STD_LOGIC_1164.ALL;

-- Uncomment the following library declaration if using
-- arithmetic functions with Signed or Unsigned values
--use IEEE.NUMERIC_STD.ALL;

-- Uncomment the following library declaration if instantiating
-- any Xilinx leaf cells in this code.
--library UNISIM;
--use UNISIM.VComponents.all;

entity mux_2_a_1 is
    Port (  a : in STD_LOGIC;
            b : in STD_LOGIC;
           sel: in STD_LOGIC;
           mux: out STD_LOGIC);
end mux_2_a_1;

architecture Behavioral of mux_2_a_1 is

begin
    mux<= a when sel='0' else b;
end Behavioral;

Guia_TP/CLP_CESE/CLP_CESE.srcs/sources_1/new/barrel_shifter_mux.vhd
----------------------------------------------------------------------------------
-- Company: 
-- Engineer: 
-- 
-- Create Date: 27.08.2026 21:52:05
-- Design Name: 
-- Module Name: barrel_shifter_mux - Behavioral
-- Project Name: 
-- Target Devices: 
-- Tool Versions: 
-- Description: Barrel shifter de 8 bits implementado con multiplexores de 2 a 1.
-- 
-- Dependencies: 
-- 
-- Revision:
-- Revision 0.01 - File Created
-- Additional Comments:
-- 
----------------------------------------------------------------------------------


library IEEE;
use IEEE.STD_LOGIC_1164.ALL;

-- Uncomment the following library declaration if using
-- arithmetic functions with Signed or Unsigned values
--use IEEE.NUMERIC_STD.ALL;

-- Uncomment the following library declaration if instantiating
-- any Xilinx leaf cells in this code.
--library UNISIM;
--use UNISIM.VComponents.all;

entity barrel_shifter_mux is
    Port (
        a   : in  STD_LOGIC_VECTOR(8-1 downto 0);
        des : in  STD_LOGIC_VECTOR(3-1 downto 0);
        s   : out STD_LOGIC_VECTOR(8-1 downto 0)
    );
end barrel_shifter_mux;

architecture Behavioral of barrel_shifter_mux is

    signal etapa_1 : STD_LOGIC_VECTOR(8-1 downto 0);
    signal etapa_2 : STD_LOGIC_VECTOR(8-1 downto 0);
    signal etapa_3 : STD_LOGIC_VECTOR(8-1 downto 0);

    signal desp_1 : STD_LOGIC_VECTOR(8-1 downto 0);
    signal desp_2 : STD_LOGIC_VECTOR(8-1 downto 0);
    signal desp_4 : STD_LOGIC_VECTOR(8-1 downto 0);

begin

    -- Desplazamientos fijos armados mediante concatenacion.
    desp_1 <= '0' & a(8-1 downto 1);
    desp_2 <= "00" & etapa_1(8-1 downto 2);
    desp_4 <= "0000" & etapa_2(8-1 downto 4);

    -- Primera etapa: desplaza 0 o 1 posicion.
    mux_desp_1 : for i in 0 to 7 generate
        mux_instance : entity work.mux_2_a_1
            port map (
                a   => a(i),
                b   => desp_1(i),
                sel => des(0),
                mux => etapa_1(i)
            );
    end generate mux_desp_1;

    -- Segunda etapa: desplaza 0 o 2 posiciones.
    mux_desp_2 : for i in 0 to 7 generate
        mux_instance : entity work.mux_2_a_1
            port map (
                a   => etapa_1(i),
                b   => desp_2(i),
                sel => des(1),
                mux => etapa_2(i)
            );
    end generate mux_desp_2;

    -- Tercera etapa: desplaza 0 o 4 posiciones.
    mux_desp_4 : for i in 0 to 7 generate
        mux_instance : entity work.mux_2_a_1
            port map (
                a   => etapa_2(i),
                b   => desp_4(i),
                sel => des(2),
                mux => etapa_3(i)
            );
    end generate mux_desp_4;
    s <= etapa_3;

end Behavioral;

Guia_TP/cocotb/waveforms/barrel_shifter_mux.vcd
$date
  Sun Aug 30 19:24:57 2026
$end
$version
  GHDL v0
$end
$timescale
  1 ps
$end
$scope module standard $end
$upscope $end
$scope module textio $end
$upscope $end
$scope module std_logic_1164 $end
$upscope $end
$scope module barrel_shifter_mux $end
$var reg 8 ! a[7:0] $end
$var reg 3 " des[2:0] $end
$var reg 8 # s[7:0] $end
$var reg 8 $ etapa_1[7:0] $end
$var reg 8 % etapa_2[7:0] $end
$var reg 8 & etapa_3[7:0] $end
$var reg 8 ' desp_1[7:0] $end
$var reg 8 ( desp_2[7:0] $end
$var reg 8 ) desp_4[7:0] $end
$scope module mux_desp_1(0) $end
$scope module mux_instance $end
$var reg 1 * a $end
$var reg 1 + b $end
$var reg 1 , sel $end
$var reg 1 - mux $end
$upscope $end
$upscope $end
$scope module mux_desp_1(1) $end
$scope module mux_instance $end
$var reg 1 . a $end
$var reg 1 / b $end
$var reg 1 0 sel $end
$var reg 1 1 mux $end
$upscope $end
$upscope $end
$scope module mux_desp_1(2) $end
$scope module mux_instance $end
$var reg 1 2 a $end
$var reg 1 3 b $end
$var reg 1 4 sel $end
$var reg 1 5 mux $end
$upscope $end
$upscope $end
$scope module mux_desp_1(3) $end
$scope module mux_instance $end
$var reg 1 6 a $end
$var reg 1 7 b $end
$var reg 1 8 sel $end
$var reg 1 9 mux $end
$upscope $end
$upscope $end
$scope module mux_desp_1(4) $end
$scope module mux_instance $end
$var reg 1 : a $end
$var reg 1 ; b $end
$var reg 1 < sel $end
$var reg 1 = mux $end
$upscope $end
$upscope $end
$scope module mux_desp_1(5) $end
$scope module mux_instance $end
$var reg 1 > a $end
$var reg 1 ? b $end
$var reg 1 @ sel $end
$var reg 1 A mux $end
$upscope $end
$upscope $end
$scope module mux_desp_1(6) $end
$scope module mux_instance $end
$var reg 1 B a $end
$var reg 1 C b $end
$var reg 1 D sel $end
$var reg 1 E mux $end
$upscope $end
$upscope $end
$scope module mux_desp_1(7) $end
$scope module mux_instance $end
$var reg 1 F a $end
$var reg 1 G b $end
$var reg 1 H sel $end
$var reg 1 I mux $end
$upscope $end
$upscope $end
$scope module mux_desp_2(0) $end
$scope module mux_instance $end
$var reg 1 J a $end
$var reg 1 K b $end
$var reg 1 L sel $end
$var reg 1 M mux $end
$upscope $end
$upscope $end
$scope module mux_desp_2(1) $end
$scope module mux_instance $end
$var reg 1 N a $end
$var reg 1 O b $end
$var reg 1 P sel $end
$var reg 1 Q mux $end
$upscope $end
$upscope $end
$scope module mux_desp_2(2) $end
$scope module mux_instance $end
$var reg 1 R a $end
$var reg 1 S b $end
$var reg 1 T sel $end
$var reg 1 U mux $end
$upscope $end
$upscope $end
$scope module mux_desp_2(3) $end
$scope module mux_instance $end
$var reg 1 V a $end
$var reg 1 W b $end
$var reg 1 X sel $end
$var reg 1 Y mux $end
$upscope $end
$upscope $end
$scope module mux_desp_2(4) $end
$scope module mux_instance $end
$var reg 1 Z a $end
$var reg 1 [ b $end
$var reg 1 \ sel $end
$var reg 1 ] mux $end
$upscope $end
$upscope $end
$scope module mux_desp_2(5) $end
$scope module mux_instance $end
$var reg 1 ^ a $end
$var reg 1 _ b $end
$var reg 1 ` sel $end
$var reg 1 a mux $end
$upscope $end
$upscope $end
$scope module mux_desp_2(6) $end
$scope module mux_instance $end
$var reg 1 b a $end
$var reg 1 c b $end
$var reg 1 d sel $end
$var reg 1 e mux $end
$upscope $end
$upscope $end
$scope module mux_desp_2(7) $end
$scope module mux_instance $end
$var reg 1 f a $end
$var reg 1 g b $end
$var reg 1 h sel $end
$var reg 1 i mux $end
$upscope $end
$upscope $end
$scope module mux_desp_4(0) $end
$scope module mux_instance $end
$var reg 1 j a $end
$var reg 1 k b $end
$var reg 1 l sel $end
$var reg 1 m mux $end
$upscope $end
$upscope $end
$scope module mux_desp_4(1) $end
$scope module mux_instance $end
$var reg 1 n a $end
$var reg 1 o b $end
$var reg 1 p sel $end
$var reg 1 q mux $end
$upscope $end
$upscope $end
$scope module mux_desp_4(2) $end
$scope module mux_instance $end
$var reg 1 r a $end
$var reg 1 s b $end
$var reg 1 t sel $end
$var reg 1 u mux $end
$upscope $end
$upscope $end
$scope module mux_desp_4(3) $end
$scope module mux_instance $end
$var reg 1 v a $end
$var reg 1 w b $end
$var reg 1 x sel $end
$var reg 1 y mux $end
$upscope $end
$upscope $end
$scope module mux_desp_4(4) $end
$scope module mux_instance $end
$var reg 1 z a $end
$var reg 1 { b $end
$var reg 1 | sel $end
$var reg 1 } mux $end
$upscope $end
$upscope $end
$scope module mux_desp_4(5) $end
$scope module mux_instance $end
$var reg 1 !" a $end
$var reg 1 "" b $end
$var reg 1 #" sel $end
$var reg 1 $" mux $end
$upscope $end
$upscope $end
$scope module mux_desp_4(6) $end
$scope module mux_instance $end
$var reg 1 %" a $end
$var reg 1 &" b $end
$var reg 1 '" sel $end
$var reg 1 (" mux $end
$upscope $end
$upscope $end
$scope module mux_desp_4(7) $end
$scope module mux_instance $end
$var reg 1 )" a $end
$var reg 1 *" b $end
$var reg 1 +" sel $end
$var reg 1 ," mux $end
$upscope $end
$upscope $end
$upscope $end
$enddefinitions $end
#0
b10110101 !
b000 "
b10110101 #
b10110101 $
b10110101 %
b10110101 &
b01011010 '
b00101101 (
b00001011 )
1*
0+
0,
1-
0.
1/
00
01
12
03
04
15
06
17
08
09
1:
1;
0<
1=
1>
0?
0@
1A
0B
1C
0D
0E
1F
0G
0H
1I
1J
1K
0L
1M
0N
0O
0P
0Q
1R
1S
0T
1U
0V
1W
0X
0Y
1Z
0[
0\
1]
1^
1_
0`
1a
0b
0c
0d
0e
1f
0g
0h
1i
1j
1k
0l
1m
0n
1o
0p
0q
1r
0s
0t
1u
0v
1w
0x
0y
1z
0{
0|
1}
1!"
0""
0#"
1$"
0%"
0&"
0'"
0("
1)"
0*"
0+"
1,"
#10000
b001 "
b01011010 #
b01011010 $
b01011010 %
b01011010 &
b00010110 (
b00000101 )
1,
0-
10
11
14
05
18
19
1<
1@
0A
1D
1E
1H
0I
0J
0K
0M
1N
1O
1Q
0R
0U
1V
0W
1Y
1[
0^
0_
0a
1b
1e
0f
0i
0j
0m
1n
0o
1q
0r
1s
0u
1v
0w
1y
0!"
0$"
1%"
1("
0)"
0,"
#20000
b010 "
b00101101 #
b10110101 $
b00101101 %
b00101101 &
b00101101 (
b00000010 )
0,
1-
00
01
04
15
08
09
0<
0@
1A
0D
0E
0H
1I
1J
1K
1L
1M
0N
0O
1P
0Q
1R
1T
1U
0V
1W
1X
1Y
0[
1\
0]
1^
1_
1`
1a
0b
1d
0e
1f
1h
1j
0k
1m
0n
1o
0q
1r
0s
1u
1v
1y
0z
0}
1!"
1$"
0%"
0("
#30000
b011 "
b00010110 #
b01011010 $
b00010110 %
b00010110 &
b00010110 (
b00000001 )
1,
0-
10
11
14
05
18
19
1<
1@
0A
1D
1E
1H
0I
0J
0K
0M
1N
1O
1Q
0R
1V
0W
0Y
1[
1]
0^
0_
0a
1b
0f
0j
1k
0m
1n
0o
1q
0v
0y
1z
1}
0!"
0$"
#40000
b100 "
b00001011 #
b10110101 $
b10110101 %
b00001011 &
b00101101 (
b00001011 )
0,
1-
00
01
04
15
08
09
0<
0@
1A
0D
0E
0H
1I
1J
1K
0L
1M
0N
0O
0P
0Q
1R
0T
1U
0V
1W
0X
0Y
0[
0\
1^
1_
0`
1a
0b
0d
0e
1f
0h
1i
1j
1l
1m
0n
1o
1p
1q
1r
0s
1t
0u
0v
1w
1x
1y
1|
0}
1!"
1#"
0%"
1'"
1)"
1+"
#50000
b101 "
b00000101 #
b01011010 $
b01011010 %
b00000101 &
b00010110 (
b00000101 )
1,
0-
10
11
14
05
18
19
1<
1@
0A
1D
1E
1H
0I
0J
0K
0M
1N
1O
1Q
0R
0U
1V
0W
1Y
1[
0^
0_
0a
1b
1e
0f
0i
0j
1n
0o
0q
0r
1s
1u
1v
0w
0y
0!"
1%"
0)"
#60000
b110 "
b00000010 #
b10110101 $
b00101101 %
b00000010 &
b00101101 (
b00000010 )
0,
1-
00
01
04
15
08
09
0<
0@
1A
0D
0E
0H
1I
1J
1K
1L
1M
0N
0O
1P
0Q
1R
1T
1U
0V
1W
1X
1Y
0[
1\
0]
1^
1_
1`
1a
0b
1d
0e
1f
1h
1j
0k
0m
0n
1o
1q
1r
0s
0u
1v
0z
1!"
0%"
#70000
b111 "
b00000001 #
b01011010 $
b00010110 %
b00000001 &
b00010110 (
b00000001 )
1,
0-
10
11
14
05
18
19
1<
1@
0A
1D
1E
1H
0I
0J
0K
0M
1N
1O
1Q
0R
1V
0W
0Y
1[
1]
0^
0_
0a
1b
0f
0j
1k
1m
1n
0o
0q
0v
1z
0!"
