Guia_TP/CLP_CESE/CLP_CESE.srcs/sources_1/new/barrel_shifter.vhd
----------------------------------------------------------------------------------
-- Company: 
-- Engineer: 
-- 
-- Create Date: 27.08.2026 21:34:59
-- Design Name: 
-- Module Name: barrel_shifter - Behavioral
-- Project Name: 
-- Target Devices: 
-- Tool Versions: 
-- Description: Barrel shifter generico con desplazamiento logico a derecha.
-- 
-- Dependencies: 
-- 
-- Revision:
-- Revision 0.01 - File Created
-- Additional Comments:
-- 
----------------------------------------------------------------------------------


library IEEE;
use IEEE.STD_LOGIC_1164.ALL;
use IEEE.NUMERIC_STD.ALL;

-- Uncomment the following library declaration if using
-- arithmetic functions with Signed or Unsigned values
--use IEEE.NUMERIC_STD.ALL;

-- Uncomment the following library declaration if instantiating
-- any Xilinx leaf cells in this code.
--library UNISIM;
--use UNISIM.VComponents.all;

entity barrel_shifter is
    Generic (
        N : integer := 8;
        M : integer := 3
    );
    Port (
        a   : in  STD_LOGIC_VECTOR(N-1 downto 0);
        des : in  STD_LOGIC_VECTOR(M-1 downto 0);
        s   : out STD_LOGIC_VECTOR(N-1 downto 0)
    );
end barrel_shifter;

architecture Behavioral of barrel_shifter is

begin

    s <= STD_LOGIC_VECTOR(shift_right(unsigned(a), to_integer(unsigned(des))));

end Behavioral;

Guia_TP/cocotb/waveforms/barrel_shifter.vcd
$date
  Sun Aug 30 19:24:50 2026
$end
$version
  GHDL v0
$end
$timescale
  1 ps
$end
$scope module standard $end
$upscope $end
$scope module textio $end
$upscope $end
$scope module std_logic_1164 $end
$upscope $end
$scope module numeric_std $end
$upscope $end
$scope module barrel_shifter $end
$var reg 8 ! a[7:0] $end
$var reg 3 " des[2:0] $end
$var reg 8 # s[7:0] $end
$upscope $end
$enddefinitions $end
#0
b10110101 !
b000 "
b10110101 #
#10000
b001 "
b01011010 #
#20000
b010 "
b00101101 #
#30000
b011 "
b00010110 #
#40000
b100 "
b00001011 #
#50000
b101 "
b00000101 #
#60000
b110 "
b00000010 #
#70000
b111 "
b00000001 #
