Guia_TP/CLP_CESE/CLP_CESE.srcs/sources_1/new/contador_N_clk.vhd
----------------------------------------------------------------------------------
-- Company: 
-- Engineer: 
-- 
-- Create Date: 28.08.2026 00:12:55
-- Design Name: 
-- Module Name: contador_N_clk - Behavioral
-- Project Name: 
-- Target Devices: 
-- Tool Versions: 
-- Description: Generador de un pulso de habilitacion cada N ciclos de reloj.
-- 
-- Dependencies: 
-- 
-- Revision:
-- Revision 0.01 - File Created
-- Additional Comments:
-- 
----------------------------------------------------------------------------------


library IEEE;
use IEEE.STD_LOGIC_1164.ALL;
use IEEE.NUMERIC_STD.ALL;
use IEEE.MATH_REAL.ALL;

-- Uncomment the following library declaration if using
-- arithmetic functions with Signed or Unsigned values
--use IEEE.NUMERIC_STD.ALL;

-- Uncomment the following library declaration if instantiating
-- any Xilinx leaf cells in this code.
--library UNISIM;
--use UNISIM.VComponents.all;

entity contador_N_clk is
    Generic (
        N : integer := 5
    );
    Port (
        rst : in  STD_LOGIC;
        clk : in  STD_LOGIC;
        s   : out STD_LOGIC
    );
end contador_N_clk;

architecture Behavioral of contador_N_clk is
    -- calculo dinamico de la cantidad de bits necesarios para contar hasta N-1
    constant M : integer := integer(ceil(log2(real(N))));
    signal q : unsigned(M-1 downto 0);

begin

    assert (N > 1)
        report "N debe ser mayor que 1"
        severity failure;

    s <= '1' when q = to_unsigned(N-1, M) else '0';

    process(clk)
    begin
        if rising_edge(clk) then
            if rst = '1' then
                q <= to_unsigned(0, M);
            elsif q = to_unsigned(N-1, M) then
                q <= to_unsigned(0, M);
            else
                q <= q + to_unsigned(1, M);
            end if;
        end if;
    end process;

end Behavioral;

Guia_TP/cocotb/waveforms/contador_N_clk.vcd
$date
  Sun Aug 30 19:25:04 2026
$end
$version
  GHDL v0
$end
$timescale
  1 ps
$end
$scope module standard $end
$upscope $end
$scope module textio $end
$upscope $end
$scope module std_logic_1164 $end
$upscope $end
$scope module numeric_std $end
$upscope $end
$scope module math_real $end
$upscope $end
$scope module contador_n_clk $end
$var reg 1 ! rst $end
$var reg 1 " clk $end
$var reg 1 # s $end
$var reg 3 $ q[2:0] $end
$upscope $end
$enddefinitions $end
#0
1!
1"
0#
bUUU $
#5000
0"
#10000
1"
b000 $
#15000
0"
#20000
1"
#25000
0"
#30000
1"
#35000
0"
#40000
1"
#41000
0!
#42000
#45000
0"
#50000
1"
b001 $
#51000
#55000
0"
#60000
1"
b010 $
#61000
#65000
0"
#70000
1"
b011 $
#71000
#75000
0"
#80000
1"
1#
b100 $
#81000
#85000
0"
#90000
1"
0#
b000 $
#91000
#95000
0"
#100000
1"
b001 $
#101000
#105000
0"
#110000
1"
b010 $
#111000
#115000
0"
#120000
1"
b011 $
#121000
#125000
0"
#130000
1"
1#
b100 $
#131000
#135000
0"
#140000
1"
0#
b000 $
#141000
#145000
0"
#150000
1"
b001 $
#151000
#155000
0"
#160000
1"
b010 $
#161000
#165000
0"
#170000
1"
b011 $
#171000
#175000
0"
#180000
1"
1#
b100 $
#181000
#185000
0"
#190000
1"
0#
b000 $
#191000
#195000
0"
#200000
1"
b001 $
#205000
0"
#210000
1"
b010 $
#215000
0"
#220000
1"
b011 $
#225000
0"
#230000
1"
1#
b100 $
#235000
0"
#240000
1"
0#
b000 $
#245000
0"
#250000
1"
b001 $
#255000
0"
#260000
1"
b010 $
#265000
0"
#270000
1"
b011 $
#275000
0"
#280000
1"
1#
b100 $
#285000
0"
#290000
1"
0#
b000 $
