Guia_TP/CLP_CESE/CLP_CESE.srcs/sources_1/new/contador_bcd_comportamiento.vhd
----------------------------------------------------------------------------------
-- Company: 
-- Engineer: 
-- 
-- Create Date: 27.08.2026 23:39:21
-- Design Name: 
-- Module Name: contador_bcd_comportamiento - Behavioral
-- Project Name: 
-- Target Devices: 
-- Tool Versions: 
-- Description: Contador BCD de un digito descripto por comportamiento.
-- 
-- Dependencies: 
-- 
-- Revision:
-- Revision 0.01 - File Created
-- Additional Comments:
-- 
----------------------------------------------------------------------------------


library IEEE;
use IEEE.STD_LOGIC_1164.ALL;
use IEEE.NUMERIC_STD.ALL;

-- Uncomment the following library declaration if using
-- arithmetic functions with Signed or Unsigned values
--use IEEE.NUMERIC_STD.ALL;

-- Uncomment the following library declaration if instantiating
-- any Xilinx leaf cells in this code.
--library UNISIM;
--use UNISIM.VComponents.all;

entity contador_bcd_comportamiento is
    Port (
        ena : in  STD_LOGIC;
        rst : in  STD_LOGIC;
        clk : in  STD_LOGIC;
        q   : out STD_LOGIC_VECTOR(4-1 downto 0)
    );
end contador_bcd_comportamiento;

architecture Behavioral of contador_bcd_comportamiento is

    signal q_now  : STD_LOGIC_VECTOR(4-1 downto 0);
    signal q_inc  : STD_LOGIC_VECTOR(4-1 downto 0);
    signal d_next : STD_LOGIC_VECTOR(4-1 downto 0);
    signal igual9 : STD_LOGIC;

begin

    -- Incrementador combinacional.
    q_inc <= STD_LOGIC_VECTOR(unsigned(q_now) + to_unsigned(1, 4));

    -- Comparador combinacional con el valor BCD 9.
    igual9 <= '1' when q_now = "1001" else '0';

    -- MUX: despues del 9 carga cero; en otro caso carga Q + 1.
    d_next <= "0000" when igual9 = '1' else q_inc;

    -- Registro de estado con reset sincrono.
    process(clk)
    begin
        if rising_edge(clk) then
            if rst = '1' then
                q_now <= (others => '0');
            elsif ena = '1' then
                q_now <= d_next;
            end if;
        end if;
    end process;

    q <= q_now;

end Behavioral;

Guia_TP/cocotb/waveforms/contador_bcd_comportamiento.vcd
$date
  Sun Aug 30 19:25:30 2026
$end
$version
  GHDL v0
$end
$timescale
  1 ps
$end
$scope module standard $end
$upscope $end
$scope module textio $end
$upscope $end
$scope module std_logic_1164 $end
$upscope $end
$scope module numeric_std $end
$upscope $end
$scope module contador_bcd_comportamiento $end
$var reg 1 ! ena $end
$var reg 1 " rst $end
$var reg 1 # clk $end
$var reg 4 $ q[3:0] $end
$var reg 4 % q_now[3:0] $end
$var reg 4 & q_inc[3:0] $end
$var reg 4 ' d_next[3:0] $end
$var reg 1 ( igual9 $end
$upscope $end
$enddefinitions $end
#0
0!
1"
1#
bUUUU $
bUUUU %
bXXXX &
bXXXX '
0(
#5000
0#
#10000
1#
b0000 $
b0000 %
b0001 &
b0001 '
#15000
0#
#20000
1#
#25000
0#
#30000
1#
#35000
0#
#40000
1#
#41000
0"
#42000
#45000
0#
#50000
1#
#51000
1!
#55000
0#
#60000
1#
b0001 $
b0001 %
b0010 &
b0010 '
#61000
#65000
0#
#70000
1#
b0010 $
b0010 %
b0011 &
b0011 '
#71000
#75000
0#
#80000
1#
b0011 $
b0011 %
b0100 &
b0100 '
#81000
#85000
0#
#90000
1#
b0100 $
b0100 %
b0101 &
b0101 '
#91000
#95000
0#
#100000
1#
b0101 $
b0101 %
b0110 &
b0110 '
#101000
#105000
0#
#110000
1#
b0110 $
b0110 %
b0111 &
b0111 '
#111000
#115000
0#
#120000
1#
b0111 $
b0111 %
b1000 &
b1000 '
#121000
#125000
0#
#130000
1#
b1000 $
b1000 %
b1001 &
b1001 '
#131000
#135000
0#
#140000
1#
b1001 $
b1001 %
b1010 &
b0000 '
1(
#141000
#145000
0#
#150000
1#
b0000 $
b0000 %
b0001 &
b0001 '
0(
#151000
#155000
0#
#160000
1#
b0001 $
b0001 %
b0010 &
b0010 '
#161000
#165000
0#
#170000
1#
b0010 $
b0010 %
b0011 &
b0011 '
#171000
#175000
0#
#180000
1#
b0011 $
b0011 %
b0100 &
b0100 '
#181000
#185000
0#
#190000
1#
b0100 $
b0100 %
b0101 &
b0101 '
#191000
#195000
0#
#200000
1#
b0101 $
b0101 %
b0110 &
b0110 '
#201000
#205000
0#
#210000
1#
b0110 $
b0110 %
b0111 &
b0111 '
#211000
#215000
0#
#220000
1#
b0111 $
b0111 %
b1000 &
b1000 '
#221000
#225000
0#
#230000
1#
b1000 $
b1000 %
b1001 &
b1001 '
#231000
#235000
0#
#240000
1#
b1001 $
b1001 %
b1010 &
b0000 '
1(
#241000
#245000
0#
#250000
1#
b0000 $
b0000 %
b0001 &
b0001 '
0(
#251000
0!
#255000
0#
#260000
1#
#261000
1!
#265000
0#
#270000
1#
b0001 $
b0001 %
b0010 &
b0010 '
#271000
#275000
0#
#280000
1#
b0010 $
b0010 %
b0011 &
b0011 '
#285000
0#
#290000
1#
b0011 $
b0011 %
b0100 &
b0100 '
#295000
0#
#300000
1#
b0100 $
b0100 %
b0101 &
b0101 '
#305000
0#
#310000
1#
b0101 $
b0101 %
b0110 &
b0110 '
#315000
0#
#320000
1#
b0110 $
b0110 %
b0111 &
b0111 '
#325000
0#
#330000
1#
b0111 $
b0111 %
b1000 &
b1000 '
#335000
0#
#340000
1#
b1000 $
b1000 %
b1001 &
b1001 '
#345000
0#
#350000
1#
b1001 $
b1001 %
b1010 &
b0000 '
1(
#355000
0#
#360000
1#
b0000 $
b0000 %
b0001 &
b0001 '
0(
#365000
0#
#370000
1#
b0001 $
b0001 %
b0010 &
b0010 '
