Guia_TP/CLP_CESE/CLP_CESE.srcs/sources_1/new/contador_binario_N_bits_comportamiento.vhd
----------------------------------------------------------------------------------
-- Company: 
-- Engineer: 
-- 
-- Create Date: 27.08.2026 23:04:31
-- Design Name: 
-- Module Name: contador_binario_N_bits_comportamiento - Behavioral
-- Project Name: 
-- Target Devices: 
-- Tool Versions: 
-- Description: Contador binario generico de N bits por comportamiento.
-- 
-- Dependencies: 
-- 
-- Revision:
-- Revision 0.01 - File Created
-- Additional Comments:
-- 
----------------------------------------------------------------------------------


library IEEE;
use IEEE.STD_LOGIC_1164.ALL;
use IEEE.NUMERIC_STD.ALL;

-- Uncomment the following library declaration if using
-- arithmetic functions with Signed or Unsigned values
--use IEEE.NUMERIC_STD.ALL;

-- Uncomment the following library declaration if instantiating
-- any Xilinx leaf cells in this code.
--library UNISIM;
--use UNISIM.VComponents.all;

entity contador_binario_N_bits_comportamiento is
    Generic (
        N : integer := 4
    );
    Port ( ena : in  STD_LOGIC;
           rst : in  STD_LOGIC;
           clk : in  STD_LOGIC;
           q   : out STD_LOGIC_VECTOR(N-1 downto 0));
end contador_binario_N_bits_comportamiento;

architecture Behavioral of contador_binario_N_bits_comportamiento is
    signal q_now, q_next: unsigned(N-1 downto 0);
begin

    process(clk)
    begin
        if rising_edge(clk) then
            if rst='1' then
                q_now<=to_unsigned(0,N);
            else
                if ena = '1' then 
                    q_now<=q_next;
                end if;
            end if;            
        end if;    
    end process;
    
    q_next <= q_now + to_unsigned(1, N);
    q <= std_logic_vector(q_now);

end Behavioral;

Guia_TP/cocotb/waveforms/contador_binario_N_bits_comportamiento.vcd
$date
  Sun Aug 30 19:25:55 2026
$end
$version
  GHDL v0
$end
$timescale
  1 ps
$end
$scope module standard $end
$upscope $end
$scope module textio $end
$upscope $end
$scope module std_logic_1164 $end
$upscope $end
$scope module numeric_std $end
$upscope $end
$scope module contador_binario_n_bits_comportamiento $end
$var reg 1 ! ena $end
$var reg 1 " rst $end
$var reg 1 # clk $end
$var reg 5 $ q[4:0] $end
$var reg 5 % q_now[4:0] $end
$var reg 5 & q_next[4:0] $end
$upscope $end
$enddefinitions $end
#0
0!
1"
1#
bUUUUU $
bUUUUU %
bXXXXX &
#5000
0#
#10000
1#
b00000 $
b00000 %
b00001 &
#15000
0#
#20000
1#
#25000
0#
#30000
1#
#35000
0#
#40000
1#
#41000
0"
#42000
#45000
0#
#50000
1#
#51000
1!
#55000
0#
#60000
1#
b00001 $
b00001 %
b00010 &
#61000
#65000
0#
#70000
1#
b00010 $
b00010 %
b00011 &
#71000
#75000
0#
#80000
1#
b00011 $
b00011 %
b00100 &
#81000
#85000
0#
#90000
1#
b00100 $
b00100 %
b00101 &
#91000
#95000
0#
#100000
1#
b00101 $
b00101 %
b00110 &
#101000
#105000
0#
#110000
1#
b00110 $
b00110 %
b00111 &
#111000
#115000
0#
#120000
1#
b00111 $
b00111 %
b01000 &
#121000
#125000
0#
#130000
1#
b01000 $
b01000 %
b01001 &
#131000
#135000
0#
#140000
1#
b01001 $
b01001 %
b01010 &
#141000
#145000
0#
#150000
1#
b01010 $
b01010 %
b01011 &
#151000
#155000
0#
#160000
1#
b01011 $
b01011 %
b01100 &
#161000
#165000
0#
#170000
1#
b01100 $
b01100 %
b01101 &
#171000
#175000
0#
#180000
1#
b01101 $
b01101 %
b01110 &
#181000
#185000
0#
#190000
1#
b01110 $
b01110 %
b01111 &
#191000
#195000
0#
#200000
1#
b01111 $
b01111 %
b10000 &
#201000
#205000
0#
#210000
1#
b10000 $
b10000 %
b10001 &
#211000
#215000
0#
#220000
1#
b10001 $
b10001 %
b10010 &
#221000
#225000
0#
#230000
1#
b10010 $
b10010 %
b10011 &
#231000
#235000
0#
#240000
1#
b10011 $
b10011 %
b10100 &
#241000
#245000
0#
#250000
1#
b10100 $
b10100 %
b10101 &
#251000
#255000
0#
#260000
1#
b10101 $
b10101 %
b10110 &
#261000
#265000
0#
#270000
1#
b10110 $
b10110 %
b10111 &
#271000
#275000
0#
#280000
1#
b10111 $
b10111 %
b11000 &
#281000
#285000
0#
#290000
1#
b11000 $
b11000 %
b11001 &
#291000
#295000
0#
#300000
1#
b11001 $
b11001 %
b11010 &
#301000
#305000
0#
#310000
1#
b11010 $
b11010 %
b11011 &
#311000
#315000
0#
#320000
1#
b11011 $
b11011 %
b11100 &
#321000
#325000
0#
#330000
1#
b11100 $
b11100 %
b11101 &
#331000
#335000
0#
#340000
1#
b11101 $
b11101 %
b11110 &
#341000
#345000
0#
#350000
1#
b11110 $
b11110 %
b11111 &
#351000
#355000
0#
#360000
1#
b11111 $
b11111 %
b00000 &
#361000
#365000
0#
#370000
1#
b00000 $
b00000 %
b00001 &
#371000
0!
#375000
0#
#380000
1#
#381000
1!
#385000
0#
#390000
1#
b00001 $
b00001 %
b00010 &
#391000
#395000
0#
#400000
1#
b00010 $
b00010 %
b00011 &
#405000
0#
#410000
1#
b00011 $
b00011 %
b00100 &
#415000
0#
#420000
1#
b00100 $
b00100 %
b00101 &
#425000
0#
#430000
1#
b00101 $
b00101 %
b00110 &
#435000
0#
#440000
1#
b00110 $
b00110 %
b00111 &
#445000
0#
#450000
1#
b00111 $
b00111 %
b01000 &
#455000
0#
#460000
1#
b01000 $
b01000 %
b01001 &
#465000
0#
#470000
1#
b01001 $
b01001 %
b01010 &
#475000
0#
#480000
1#
b01010 $
b01010 %
b01011 &
#485000
0#
#490000
1#
b01011 $
b01011 %
b01100 &
