Guia_TP/CLP_CESE/CLP_CESE.srcs/sources_1/new/registro_N_bits.vhd
----------------------------------------------------------------------------------
-- Company: 
-- Engineer: 
-- 
-- Create Date: 27.08.2026 23:34:00
-- Design Name: 
-- Module Name: registro_N_bits - Behavioral
-- Project Name: 
-- Target Devices: 
-- Tool Versions: 
-- Description: Registro paralelo generico de N bits con enable y reset sincrono.
-- 
-- Dependencies: 
-- 
-- Revision:
-- Revision 0.01 - File Created
-- Additional Comments:
-- 
----------------------------------------------------------------------------------


library IEEE;
use IEEE.STD_LOGIC_1164.ALL;

-- Uncomment the following library declaration if using
-- arithmetic functions with Signed or Unsigned values
--use IEEE.NUMERIC_STD.ALL;

-- Uncomment the following library declaration if instantiating
-- any Xilinx leaf cells in this code.
--library UNISIM;
--use UNISIM.VComponents.all;

entity registro_N_bits is
    Generic (
        N : integer := 4
    );
    Port (
        d   : in  STD_LOGIC_VECTOR(N-1 downto 0);
        ena : in  STD_LOGIC;
        rst : in  STD_LOGIC;
        clk : in  STD_LOGIC;
        q   : out STD_LOGIC_VECTOR(N-1 downto 0)
    );
end registro_N_bits;

architecture Behavioral of registro_N_bits is

begin

    process(clk)
    begin
        if rising_edge(clk) then
            if rst = '1' then
                q <= (others => '0');
            elsif ena = '1' then
                q <= d;
            end if;
        end if;
    end process;

end Behavioral;

Guia_TP/CLP_CESE/CLP_CESE.srcs/sources_1/new/mux_2_a_1.vhd
----------------------------------------------------------------------------------
-- Company: 
-- Engineer: 
-- 
-- Create Date: 27.08.2026 20:36:34
-- Design Name: 
-- Module Name: mux_2_a_1 - Behavioral
-- Project Name: 
-- Target Devices: 
-- Tool Versions: 
-- Description: Multiplexor combinacional de dos entradas de 1 bit.
-- 
-- Dependencies: 
-- 
-- Revision:
-- Revision 0.01 - File Created
-- Additional Comments:
-- 
----------------------------------------------------------------------------------


library IEEE;
use IEEE.STD_LOGIC_1164.ALL;

-- Uncomment the following library declaration if using
-- arithmetic functions with Signed or Unsigned values
--use IEEE.NUMERIC_STD.ALL;

-- Uncomment the following library declaration if instantiating
-- any Xilinx leaf cells in this code.
--library UNISIM;
--use UNISIM.VComponents.all;

entity mux_2_a_1 is
    Port (  a : in STD_LOGIC;
            b : in STD_LOGIC;
           sel: in STD_LOGIC;
           mux: out STD_LOGIC);
end mux_2_a_1;

architecture Behavioral of mux_2_a_1 is

begin
    mux<= a when sel='0' else b;
end Behavioral;

Guia_TP/CLP_CESE/CLP_CESE.srcs/sources_1/new/comparador_igual.vhd
----------------------------------------------------------------------------------
-- Company: 
-- Engineer: 
-- 
-- Create Date: 27.08.2026 23:27:44
-- Design Name: 
-- Module Name: comparador_igual - Behavioral
-- Project Name: 
-- Target Devices: 
-- Tool Versions: 
-- Description: Comparador de igualdad generico para dos palabras de N bits.
-- 
-- Dependencies: 
-- 
-- Revision:
-- Revision 0.01 - File Created
-- Additional Comments:
-- 
----------------------------------------------------------------------------------


library IEEE;
use IEEE.STD_LOGIC_1164.ALL;

-- Uncomment the following library declaration if using
-- arithmetic functions with Signed or Unsigned values
--use IEEE.NUMERIC_STD.ALL;

-- Uncomment the following library declaration if instantiating
-- any Xilinx leaf cells in this code.
--library UNISIM;
--use UNISIM.VComponents.all;

entity comparador_igual is
    Generic (
        N : integer := 4
    );
    Port ( a     : in  STD_LOGIC_VECTOR(N-1 downto 0);
           b     : in  STD_LOGIC_VECTOR(N-1 downto 0);
           igual : out STD_LOGIC
    );
end comparador_igual;

architecture Behavioral of comparador_igual is

begin
    igual <= '1' when a = b else '0';

end Behavioral;

Guia_TP/CLP_CESE/CLP_CESE.srcs/sources_1/new/adder_1_bit.vhd
----------------------------------------------------------------------------------
-- Company: 
-- Engineer: 
-- 
-- Create Date: 27.08.2026 19:23:36
-- Design Name: 
-- Module Name: adder_1_bit - Behavioral
-- Project Name: 
-- Target Devices: 
-- Tool Versions: 
-- Description: Sumador completo de 1 bit con acarreo de entrada y salida.
-- 
-- Dependencies: 
-- 
-- Revision:
-- Revision 0.01 - File Created
-- Additional Comments:
-- 
----------------------------------------------------------------------------------


library IEEE;
use IEEE.STD_LOGIC_1164.ALL;

-- Uncomment the following library declaration if using
-- arithmetic functions with Signed or Unsigned values
--use IEEE.NUMERIC_STD.ALL;

-- Uncomment the following library declaration if instantiating
-- any Xilinx leaf cells in this code.
--library UNISIM;
--use UNISIM.VComponents.all;

entity adder_1_bit is
    Port ( ci : in STD_LOGIC;
           a : in STD_LOGIC;
           b : in STD_LOGIC;
           s : out STD_LOGIC;
           co : out STD_LOGIC);
end adder_1_bit;

architecture Behavioral of adder_1_bit is

begin
    
    s<= a xor b xor ci;
    co<= (a and b) or (b and ci) or (a and ci);

end Behavioral;

Guia_TP/CLP_CESE/CLP_CESE.srcs/sources_1/new/adder_4_bits.vhd
----------------------------------------------------------------------------------
-- Company: 
-- Engineer: 
-- 
-- Create Date: 27.08.2026 19:49:11
-- Design Name: 
-- Module Name: adder_4_bits - Behavioral
-- Project Name: 
-- Target Devices: 
-- Tool Versions: 
-- Description: Sumador estructural de 4 bits formado por cuatro sumadores completos.
-- 
-- Dependencies: 
-- 
-- Revision:
-- Revision 0.01 - File Created
-- Additional Comments:
-- 
----------------------------------------------------------------------------------


library IEEE;
use IEEE.STD_LOGIC_1164.ALL;

library work;
use work.adder_1_bit;
-- Uncomment the following library declaration if using
-- arithmetic functions with Signed or Unsigned values
--use IEEE.NUMERIC_STD.ALL;

-- Uncomment the following library declaration if instantiating
-- any Xilinx leaf cells in this code.
--library UNISIM;
--use UNISIM.VComponents.all;

entity adder_4_bits is
    Port ( ci : in STD_LOGIC;
            a : in STD_LOGIC_VECTOR(4-1 downto 0);
            b : in STD_LOGIC_VECTOR(4-1 downto 0);
            s : out STD_LOGIC_VECTOR(4-1 downto 0);
           co : out STD_LOGIC);
end adder_4_bits;

architecture Behavioral of adder_4_bits is
    signal c_vector : STD_LOGIC_VECTOR(5-1 downto 0);
begin
    c_vector(0) <= ci;
    co <= c_vector(4);

    ciclo : for i in 0 to 3 generate
        adder_1_bit_instance : entity work.adder_1_bit
            port map (
                ci => c_vector(i),
                a  => a(i),
                b  => b(i),
                s  => s(i),
                co => c_vector(i + 1)
            );
    end generate ciclo;
end Behavioral;

Guia_TP/CLP_CESE/CLP_CESE.srcs/sources_1/new/contador_bcd.vhd
----------------------------------------------------------------------------------
-- Company: 
-- Engineer: 
-- 
-- Create Date: 27.08.2026 23:14:29
-- Design Name: 
-- Module Name: contador_bcd - Behavioral
-- Project Name: 
-- Target Devices: 
-- Tool Versions: 
-- Description: Contador BCD estructural de un digito con enable y acarreo.
-- 
-- Dependencies: 
-- 
-- Revision:
-- Revision 0.01 - File Created
-- Additional Comments:
-- 
----------------------------------------------------------------------------------


library IEEE;
use IEEE.STD_LOGIC_1164.ALL;

-- Uncomment the following library declaration if using
-- arithmetic functions with Signed or Unsigned values
--use IEEE.NUMERIC_STD.ALL;

-- Uncomment the following library declaration if instantiating
-- any Xilinx leaf cells in this code.
--library UNISIM;
--use UNISIM.VComponents.all;

entity contador_bcd is
    Port ( ena : in  STD_LOGIC;
           rst : in  STD_LOGIC;
           clk : in  STD_LOGIC;
           q   : out STD_LOGIC_VECTOR(4-1 downto 0);
           co  : out STD_LOGIC);
end contador_bcd;

architecture Behavioral of contador_bcd is

    signal d_reg  : STD_LOGIC_VECTOR(3 downto 0);
    signal q_reg  : STD_LOGIC_VECTOR(3 downto 0);
    signal q_inc  : STD_LOGIC_VECTOR(3 downto 0);
    signal igual9 : STD_LOGIC;
    signal co_aux : STD_LOGIC;

begin

    q <= q_reg;
    co <= ena and igual9;

    adder_instance : entity work.adder_4_bits
        port map (
            ci => '0',
            a  => q_reg,
            b  => "0001",
            s  => q_inc,
            co => co_aux
        );

    comparador_instance : entity work.comparador_igual
        generic map (
            N => 4
        )
        port map (
            a     => q_reg,
            b     => "1001",
            igual => igual9
        );

    -- Cuando el valor actual es 9, el siguiente valor debe ser 0.
    mux_bcd : for i in 0 to 3 generate
        mux_instance : entity work.mux_2_a_1
            port map (
                a   => q_inc(i),
                b   => '0',
                sel => igual9,
                mux => d_reg(i)
            );
    end generate mux_bcd;

    registro_instance : entity work.registro_N_bits
        generic map (
            N => 4
        )
        port map (
            d   => d_reg,
            ena => ena,
            rst => rst,
            clk => clk,
            q   => q_reg
        );

end Behavioral;

Guia_TP/CLP_CESE/CLP_CESE.srcs/sources_1/new/contador_bcd_4_digitos.vhd
----------------------------------------------------------------------------------
-- Company: 
-- Engineer: 
-- 
-- Create Date: 27.08.2026 23:56:03
-- Design Name: 
-- Module Name: contador_bcd_4_digitos - Behavioral
-- Project Name: 
-- Target Devices: 
-- Tool Versions: 
-- Description: Contador BCD de cuatro digitos mediante contadores encadenados.
-- 
-- Dependencies: 
-- 
-- Revision:
-- Revision 0.01 - File Created
-- Additional Comments:
-- 
----------------------------------------------------------------------------------


library IEEE;
use IEEE.STD_LOGIC_1164.ALL;

-- Uncomment the following library declaration if using
-- arithmetic functions with Signed or Unsigned values
--use IEEE.NUMERIC_STD.ALL;

-- Uncomment the following library declaration if instantiating
-- any Xilinx leaf cells in this code.
--library UNISIM;
--use UNISIM.VComponents.all;

entity contador_bcd_4_digitos is
    Port (
        ena  : in  STD_LOGIC;
        rst  : in  STD_LOGIC;
        clk  : in  STD_LOGIC;
        bcd0 : out STD_LOGIC_VECTOR(3 downto 0);
        bcd1 : out STD_LOGIC_VECTOR(3 downto 0);
        bcd2 : out STD_LOGIC_VECTOR(3 downto 0);
        bcd3 : out STD_LOGIC_VECTOR(3 downto 0);
        co   : out STD_LOGIC
    );
end contador_bcd_4_digitos;

architecture Behavioral of contador_bcd_4_digitos is

    signal ena_aux : STD_LOGIC_VECTOR(4 downto 0);
    signal q_aux   : STD_LOGIC_VECTOR(15 downto 0);

begin

    ena_aux(0) <= ena;
    co <= ena_aux(4);

    bcd0 <= q_aux(3 downto 0);
    bcd1 <= q_aux(7 downto 4);
    bcd2 <= q_aux(11 downto 8);
    bcd3 <= q_aux(15 downto 12);

    digitos : for i in 0 to 3 generate
        contador_instance : entity work.contador_bcd
            port map (
                ena => ena_aux(i),
                rst => rst,
                clk => clk,
                q   => q_aux(4*i+3 downto 4*i),
                co  => ena_aux(i + 1)
            );
    end generate digitos;

end Behavioral;

Guia_TP/cocotb/waveforms/contador_bcd_4_digitos.vcd
$date
  Sun Aug 30 19:25:23 2026
$end
$version
  GHDL v0
$end
$timescale
  1 ps
$end
$scope module standard $end
$upscope $end
$scope module textio $end
$upscope $end
$scope module std_logic_1164 $end
$upscope $end
$scope module contador_bcd_4_digitos $end
$var reg 1 ! ena $end
$var reg 1 " rst $end
$var reg 1 # clk $end
$var reg 4 $ bcd0[3:0] $end
$var reg 4 % bcd1[3:0] $end
$var reg 4 & bcd2[3:0] $end
$var reg 4 ' bcd3[3:0] $end
$var reg 1 ( co $end
$var reg 5 ) ena_aux[4:0] $end
$var reg 16 * q_aux[15:0] $end
$scope module digitos(0) $end
$scope module contador_instance $end
$var reg 1 + ena $end
$var reg 1 , rst $end
$var reg 1 - clk $end
$var reg 4 . q[3:0] $end
$var reg 1 / co $end
$var reg 4 0 d_reg[3:0] $end
$var reg 4 1 q_reg[3:0] $end
$var reg 4 2 q_inc[3:0] $end
$var reg 1 3 igual9 $end
$var reg 1 4 co_aux $end
$scope module adder_instance $end
$var reg 1 5 ci $end
$var reg 4 6 a[3:0] $end
$var reg 4 7 b[3:0] $end
$var reg 4 8 s[3:0] $end
$var reg 1 9 co $end
$var reg 5 : c_vector[4:0] $end
$scope module ciclo(0) $end
$scope module adder_1_bit_instance $end
$var reg 1 ; ci $end
$var reg 1 < a $end
$var reg 1 = b $end
$var reg 1 > s $end
$var reg 1 ? co $end
$upscope $end
$upscope $end
$scope module ciclo(1) $end
$scope module adder_1_bit_instance $end
$var reg 1 @ ci $end
$var reg 1 A a $end
$var reg 1 B b $end
$var reg 1 C s $end
$var reg 1 D co $end
$upscope $end
$upscope $end
$scope module ciclo(2) $end
$scope module adder_1_bit_instance $end
$var reg 1 E ci $end
$var reg 1 F a $end
$var reg 1 G b $end
$var reg 1 H s $end
$var reg 1 I co $end
$upscope $end
$upscope $end
$scope module ciclo(3) $end
$scope module adder_1_bit_instance $end
$var reg 1 J ci $end
$var reg 1 K a $end
$var reg 1 L b $end
$var reg 1 M s $end
$var reg 1 N co $end
$upscope $end
$upscope $end
$upscope $end
$scope module comparador_instance $end
$var reg 4 O a[3:0] $end
$var reg 4 P b[3:0] $end
$var reg 1 Q igual $end
$upscope $end
$scope module mux_bcd(0) $end
$scope module mux_instance $end
$var reg 1 R a $end
$var reg 1 S b $end
$var reg 1 T sel $end
$var reg 1 U mux $end
$upscope $end
$upscope $end
$scope module mux_bcd(1) $end
$scope module mux_instance $end
$var reg 1 V a $end
$var reg 1 W b $end
$var reg 1 X sel $end
$var reg 1 Y mux $end
$upscope $end
$upscope $end
$scope module mux_bcd(2) $end
$scope module mux_instance $end
$var reg 1 Z a $end
$var reg 1 [ b $end
$var reg 1 \ sel $end
$var reg 1 ] mux $end
$upscope $end
$upscope $end
$scope module mux_bcd(3) $end
$scope module mux_instance $end
$var reg 1 ^ a $end
$var reg 1 _ b $end
$var reg 1 ` sel $end
$var reg 1 a mux $end
$upscope $end
$upscope $end
$scope module registro_instance $end
$var reg 4 b d[3:0] $end
$var reg 1 c ena $end
$var reg 1 d rst $end
$var reg 1 e clk $end
$var reg 4 f q[3:0] $end
$upscope $end
$upscope $end
$upscope $end
$scope module digitos(1) $end
$scope module contador_instance $end
$var reg 1 g ena $end
$var reg 1 h rst $end
$var reg 1 i clk $end
$var reg 4 j q[3:0] $end
$var reg 1 k co $end
$var reg 4 l d_reg[3:0] $end
$var reg 4 m q_reg[3:0] $end
$var reg 4 n q_inc[3:0] $end
$var reg 1 o igual9 $end
$var reg 1 p co_aux $end
$scope module adder_instance $end
$var reg 1 q ci $end
$var reg 4 r a[3:0] $end
$var reg 4 s b[3:0] $end
$var reg 4 t s[3:0] $end
$var reg 1 u co $end
$var reg 5 v c_vector[4:0] $end
$scope module ciclo(0) $end
$scope module adder_1_bit_instance $end
$var reg 1 w ci $end
$var reg 1 x a $end
$var reg 1 y b $end
$var reg 1 z s $end
$var reg 1 { co $end
$upscope $end
$upscope $end
$scope module ciclo(1) $end
$scope module adder_1_bit_instance $end
$var reg 1 | ci $end
$var reg 1 } a $end
$var reg 1 !" b $end
$var reg 1 "" s $end
$var reg 1 #" co $end
$upscope $end
$upscope $end
$scope module ciclo(2) $end
$scope module adder_1_bit_instance $end
$var reg 1 $" ci $end
$var reg 1 %" a $end
$var reg 1 &" b $end
$var reg 1 '" s $end
$var reg 1 (" co $end
$upscope $end
$upscope $end
$scope module ciclo(3) $end
$scope module adder_1_bit_instance $end
$var reg 1 )" ci $end
$var reg 1 *" a $end
$var reg 1 +" b $end
$var reg 1 ," s $end
$var reg 1 -" co $end
$upscope $end
$upscope $end
$upscope $end
$scope module comparador_instance $end
$var reg 4 ." a[3:0] $end
$var reg 4 /" b[3:0] $end
$var reg 1 0" igual $end
$upscope $end
$scope module mux_bcd(0) $end
$scope module mux_instance $end
$var reg 1 1" a $end
$var reg 1 2" b $end
$var reg 1 3" sel $end
$var reg 1 4" mux $end
$upscope $end
$upscope $end
$scope module mux_bcd(1) $end
$scope module mux_instance $end
$var reg 1 5" a $end
$var reg 1 6" b $end
$var reg 1 7" sel $end
$var reg 1 8" mux $end
$upscope $end
$upscope $end
$scope module mux_bcd(2) $end
$scope module mux_instance $end
$var reg 1 9" a $end
$var reg 1 :" b $end
$var reg 1 ;" sel $end
$var reg 1 <" mux $end
$upscope $end
$upscope $end
$scope module mux_bcd(3) $end
$scope module mux_instance $end
$var reg 1 =" a $end
$var reg 1 >" b $end
$var reg 1 ?" sel $end
$var reg 1 @" mux $end
$upscope $end
$upscope $end
$scope module registro_instance $end
$var reg 4 A" d[3:0] $end
$var reg 1 B" ena $end
$var reg 1 C" rst $end
$var reg 1 D" clk $end
$var reg 4 E" q[3:0] $end
$upscope $end
$upscope $end
$upscope $end
$scope module digitos(2) $end
$scope module contador_instance $end
$var reg 1 F" ena $end
$var reg 1 G" rst $end
$var reg 1 H" clk $end
$var reg 4 I" q[3:0] $end
$var reg 1 J" co $end
$var reg 4 K" d_reg[3:0] $end
$var reg 4 L" q_reg[3:0] $end
$var reg 4 M" q_inc[3:0] $end
$var reg 1 N" igual9 $end
$var reg 1 O" co_aux $end
$scope module adder_instance $end
$var reg 1 P" ci $end
$var reg 4 Q" a[3:0] $end
$var reg 4 R" b[3:0] $end
$var reg 4 S" s[3:0] $end
$var reg 1 T" co $end
$var reg 5 U" c_vector[4:0] $end
$scope module ciclo(0) $end
$scope module adder_1_bit_instance $end
$var reg 1 V" ci $end
$var reg 1 W" a $end
$var reg 1 X" b $end
$var reg 1 Y" s $end
$var reg 1 Z" co $end
$upscope $end
$upscope $end
$scope module ciclo(1) $end
$scope module adder_1_bit_instance $end
$var reg 1 [" ci $end
$var reg 1 \" a $end
$var reg 1 ]" b $end
$var reg 1 ^" s $end
$var reg 1 _" co $end
$upscope $end
$upscope $end
$scope module ciclo(2) $end
$scope module adder_1_bit_instance $end
$var reg 1 `" ci $end
$var reg 1 a" a $end
$var reg 1 b" b $end
$var reg 1 c" s $end
$var reg 1 d" co $end
$upscope $end
$upscope $end
$scope module ciclo(3) $end
$scope module adder_1_bit_instance $end
$var reg 1 e" ci $end
$var reg 1 f" a $end
$var reg 1 g" b $end
$var reg 1 h" s $end
$var reg 1 i" co $end
$upscope $end
$upscope $end
$upscope $end
$scope module comparador_instance $end
$var reg 4 j" a[3:0] $end
$var reg 4 k" b[3:0] $end
$var reg 1 l" igual $end
$upscope $end
$scope module mux_bcd(0) $end
$scope module mux_instance $end
$var reg 1 m" a $end
$var reg 1 n" b $end
$var reg 1 o" sel $end
$var reg 1 p" mux $end
$upscope $end
$upscope $end
$scope module mux_bcd(1) $end
$scope module mux_instance $end
$var reg 1 q" a $end
$var reg 1 r" b $end
$var reg 1 s" sel $end
$var reg 1 t" mux $end
$upscope $end
$upscope $end
$scope module mux_bcd(2) $end
$scope module mux_instance $end
$var reg 1 u" a $end
$var reg 1 v" b $end
$var reg 1 w" sel $end
$var reg 1 x" mux $end
$upscope $end
$upscope $end
$scope module mux_bcd(3) $end
$scope module mux_instance $end
$var reg 1 y" a $end
$var reg 1 z" b $end
$var reg 1 {" sel $end
$var reg 1 |" mux $end
$upscope $end
$upscope $end
$scope module registro_instance $end
$var reg 4 }" d[3:0] $end
$var reg 1 !# ena $end
$var reg 1 "# rst $end
$var reg 1 ## clk $end
$var reg 4 $# q[3:0] $end
$upscope $end
$upscope $end
$upscope $end
$scope module digitos(3) $end
$scope module contador_instance $end
$var reg 1 %# ena $end
$var reg 1 &# rst $end
$var reg 1 '# clk $end
$var reg 4 (# q[3:0] $end
$var reg 1 )# co $end
$var reg 4 *# d_reg[3:0] $end
$var reg 4 +# q_reg[3:0] $end
$var reg 4 ,# q_inc[3:0] $end
$var reg 1 -# igual9 $end
$var reg 1 .# co_aux $end
$scope module adder_instance $end
$var reg 1 /# ci $end
$var reg 4 0# a[3:0] $end
$var reg 4 1# b[3:0] $end
$var reg 4 2# s[3:0] $end
$var reg 1 3# co $end
$var reg 5 4# c_vector[4:0] $end
$scope module ciclo(0) $end
$scope module adder_1_bit_instance $end
$var reg 1 5# ci $end
$var reg 1 6# a $end
$var reg 1 7# b $end
$var reg 1 8# s $end
$var reg 1 9# co $end
$upscope $end
$upscope $end
$scope module ciclo(1) $end
$scope module adder_1_bit_instance $end
$var reg 1 :# ci $end
$var reg 1 ;# a $end
$var reg 1 <# b $end
$var reg 1 =# s $end
$var reg 1 ># co $end
$upscope $end
$upscope $end
$scope module ciclo(2) $end
$scope module adder_1_bit_instance $end
$var reg 1 ?# ci $end
$var reg 1 @# a $end
$var reg 1 A# b $end
$var reg 1 B# s $end
$var reg 1 C# co $end
$upscope $end
$upscope $end
$scope module ciclo(3) $end
$scope module adder_1_bit_instance $end
$var reg 1 D# ci $end
$var reg 1 E# a $end
$var reg 1 F# b $end
$var reg 1 G# s $end
$var reg 1 H# co $end
$upscope $end
$upscope $end
$upscope $end
$scope module comparador_instance $end
$var reg 4 I# a[3:0] $end
$var reg 4 J# b[3:0] $end
$var reg 1 K# igual $end
$upscope $end
$scope module mux_bcd(0) $end
$scope module mux_instance $end
$var reg 1 L# a $end
$var reg 1 M# b $end
$var reg 1 N# sel $end
$var reg 1 O# mux $end
$upscope $end
$upscope $end
$scope module mux_bcd(1) $end
$scope module mux_instance $end
$var reg 1 P# a $end
$var reg 1 Q# b $end
$var reg 1 R# sel $end
$var reg 1 S# mux $end
$upscope $end
$upscope $end
$scope module mux_bcd(2) $end
$scope module mux_instance $end
$var reg 1 T# a $end
$var reg 1 U# b $end
$var reg 1 V# sel $end
$var reg 1 W# mux $end
$upscope $end
$upscope $end
$scope module mux_bcd(3) $end
$scope module mux_instance $end
$var reg 1 X# a $end
$var reg 1 Y# b $end
$var reg 1 Z# sel $end
$var reg 1 [# mux $end
$upscope $end
$upscope $end
$scope module registro_instance $end
$var reg 4 \# d[3:0] $end
$var reg 1 ]# ena $end
$var reg 1 ^# rst $end
$var reg 1 _# clk $end
$var reg 4 `# q[3:0] $end
$upscope $end
$upscope $end
$upscope $end
$upscope $end
$enddefinitions $end
#0
0!
1"
1#
bUUUU $
bUUUU %
bUUUU &
bUUUU '
0(
b00000 )
bUUUUUUUUUUUUUUUU *
0+
1,
1-
bUUUU .
0/
bUUUU 0
bUUUU 1
bUUUU 2
03
U4
05
bUUUU 6
b0001 7
bUUUU 8
U9
bUUUU0 :
0;
U<
1=
U>
U?
U@
UA
0B
UC
UD
UE
UF
0G
UH
UI
UJ
UK
0L
UM
UN
bUUUU O
b1001 P
0Q
UR
0S
0T
UU
UV
0W
0X
UY
UZ
0[
0\
U]
U^
0_
0`
Ua
bUUUU b
0c
1d
1e
bUUUU f
0g
1h
1i
bUUUU j
0k
bUUUU l
bUUUU m
bUUUU n
0o
Up
0q
bUUUU r
b0001 s
bUUUU t
Uu
bUUUU0 v
0w
Ux
1y
Uz
U{
U|
U}
0!"
U""
U#"
U$"
U%"
0&"
U'"
U("
U)"
U*"
0+"
U,"
U-"
bUUUU ."
b1001 /"
00"
U1"
02"
03"
U4"
U5"
06"
07"
U8"
U9"
0:"
0;"
U<"
U="
0>"
0?"
U@"
bUUUU A"
0B"
1C"
1D"
bUUUU E"
0F"
1G"
1H"
bUUUU I"
0J"
bUUUU K"
bUUUU L"
bUUUU M"
0N"
UO"
0P"
bUUUU Q"
b0001 R"
bUUUU S"
UT"
bUUUU0 U"
0V"
UW"
1X"
UY"
UZ"
U["
U\"
0]"
U^"
U_"
U`"
Ua"
0b"
Uc"
Ud"
Ue"
Uf"
0g"
Uh"
Ui"
bUUUU j"
b1001 k"
0l"
Um"
0n"
0o"
Up"
Uq"
0r"
0s"
Ut"
Uu"
0v"
0w"
Ux"
Uy"
0z"
0{"
U|"
bUUUU }"
0!#
1"#
1##
bUUUU $#
0%#
1&#
1'#
bUUUU (#
0)#
bUUUU *#
bUUUU +#
bUUUU ,#
0-#
U.#
0/#
bUUUU 0#
b0001 1#
bUUUU 2#
U3#
bUUUU0 4#
05#
U6#
17#
U8#
U9#
U:#
U;#
0<#
U=#
U>#
U?#
U@#
0A#
UB#
UC#
UD#
UE#
0F#
UG#
UH#
bUUUU I#
b1001 J#
0K#
UL#
0M#
0N#
UO#
UP#
0Q#
0R#
US#
UT#
0U#
0V#
UW#
UX#
0Y#
0Z#
U[#
bUUUU \#
0]#
1^#
1_#
bUUUU `#
#5000
0#
0-
0e
0i
0D"
0H"
0##
0'#
0_#
#10000
1#
b0000 $
b0000 %
b0000 &
b0000 '
b0000000000000000 *
1-
b0000 .
b0001 0
b0000 1
b0001 2
04
b0000 6
b0001 8
09
b00000 :
0<
1>
0?
0@
0A
0C
0D
0E
0F
0H
0I
0J
0K
0M
0N
b0000 O
1R
1U
0V
0Y
0Z
0]
0^
0a
b0001 b
1e
b0000 f
1i
b0000 j
b0001 l
b0000 m
b0001 n
0p
b0000 r
b0001 t
0u
b00000 v
0x
1z
0{
0|
0}
0""
0#"
0$"
0%"
0'"
0("
0)"
0*"
0,"
0-"
b0000 ."
11"
14"
05"
08"
09"
0<"
0="
0@"
b0001 A"
1D"
b0000 E"
1H"
b0000 I"
b0001 K"
b0000 L"
b0001 M"
0O"
b0000 Q"
b0001 S"
0T"
b00000 U"
0W"
1Y"
0Z"
0["
0\"
0^"
0_"
0`"
0a"
0c"
0d"
0e"
0f"
0h"
0i"
b0000 j"
1m"
1p"
0q"
0t"
0u"
0x"
0y"
0|"
b0001 }"
1##
b0000 $#
1'#
b0000 (#
b0001 *#
b0000 +#
b0001 ,#
0.#
b0000 0#
b0001 2#
03#
b00000 4#
06#
18#
09#
0:#
0;#
0=#
0>#
0?#
0@#
0B#
0C#
0D#
0E#
0G#
0H#
b0000 I#
1L#
1O#
0P#
0S#
0T#
0W#
0X#
0[#
b0001 \#
1_#
b0000 `#
#15000
0#
0-
0e
0i
0D"
0H"
0##
0'#
0_#
#20000
1#
1-
1e
1i
1D"
1H"
1##
1'#
1_#
#25000
0#
0-
0e
0i
0D"
0H"
0##
0'#
0_#
#30000
1#
1-
1e
1i
1D"
1H"
1##
1'#
1_#
#35000
0#
0-
0e
0i
0D"
0H"
0##
0'#
0_#
#40000
1#
1-
1e
1i
1D"
1H"
1##
1'#
1_#
#41000
0"
0,
0d
0h
0C"
0G"
0"#
0&#
0^#
#42000
#45000
0#
0-
0e
0i
0D"
0H"
0##
0'#
0_#
#50000
1#
1-
1e
1i
1D"
1H"
1##
1'#
1_#
#51000
1!
b00001 )
1+
1c
#55000
0#
0-
0e
0i
0D"
0H"
0##
0'#
0_#
#60000
1#
b0001 $
b0000000000000001 *
1-
b0001 .
b0010 0
b0001 1
b0010 2
b0001 6
b0010 8
b00010 :
1<
0>
1?
1@
1C
b0001 O
0R
0U
1V
1Y
b0010 b
1e
b0001 f
1i
1D"
1H"
1##
1'#
1_#
#61000
#65000
0#
0-
0e
0i
0D"
0H"
0##
0'#
0_#
#70000
1#
b0010 $
b0000000000000010 *
1-
b0010 .
b0011 0
b0010 1
b0011 2
b0010 6
b0011 8
b00000 :
0<
1>
0?
0@
1A
1C
0D
0E
0H
b0010 O
1R
1U
1V
1Y
0Z
0]
b0011 b
1e
b0010 f
1i
1D"
1H"
1##
1'#
1_#
#71000
#75000
0#
0-
0e
0i
0D"
0H"
0##
0'#
0_#
#80000
1#
b0011 $
b0000000000000011 *
1-
b0011 .
b0100 0
b0011 1
b0100 2
b0011 6
b0100 8
b00110 :
1<
0>
1?
1@
0C
1D
1E
1H
b0011 O
0R
0U
0V
0Y
1Z
1]
b0100 b
1e
b0011 f
1i
1D"
1H"
1##
1'#
1_#
#81000
#85000
0#
0-
0e
0i
0D"
0H"
0##
0'#
0_#
#90000
1#
b0100 $
b0000000000000100 *
1-
b0100 .
b0101 0
b0100 1
b0101 2
b0100 6
b0101 8
b00000 :
0<
1>
0?
0@
0A
0C
0D
0E
1F
1H
0I
0J
0M
b0100 O
1R
1U
0V
0Y
1Z
1]
0^
0a
b0101 b
1e
b0100 f
1i
1D"
1H"
1##
1'#
1_#
#91000
#95000
0#
0-
0e
0i
0D"
0H"
0##
0'#
0_#
#100000
1#
b0101 $
b0000000000000101 *
1-
b0101 .
b0110 0
b0101 1
b0110 2
b0101 6
b0110 8
b00010 :
1<
0>
1?
1@
1C
b0101 O
0R
0U
1V
1Y
b0110 b
1e
b0101 f
1i
1D"
1H"
1##
1'#
1_#
#101000
#105000
0#
0-
0e
0i
0D"
0H"
0##
0'#
0_#
#110000
1#
b0110 $
b0000000000000110 *
1-
b0110 .
b0111 0
b0110 1
b0111 2
b0110 6
b0111 8
b00000 :
0<
1>
0?
0@
1A
1C
0D
0E
1H
0I
0J
0M
b0110 O
1R
1U
1V
1Y
1Z
1]
0^
0a
b0111 b
1e
b0110 f
1i
1D"
1H"
1##
1'#
1_#
#111000
#115000
0#
0-
0e
0i
0D"
0H"
0##
0'#
0_#
#120000
1#
b0111 $
b0000000000000111 *
1-
b0111 .
b1000 0
b0111 1
b1000 2
b0111 6
b1000 8
b01110 :
1<
0>
1?
1@
0C
1D
1E
0H
1I
1J
1M
b0111 O
0R
0U
0V
0Y
0Z
0]
1^
1a
b1000 b
1e
b0111 f
1i
1D"
1H"
1##
1'#
1_#
#121000
#125000
0#
0-
0e
0i
0D"
0H"
0##
0'#
0_#
#130000
1#
b1000 $
b0000000000001000 *
1-
b1000 .
b1001 0
b1000 1
b1001 2
04
b1000 6
b1001 8
09
b00000 :
0<
1>
0?
0@
0A
0C
0D
0E
0F
0H
0I
0J
1K
1M
0N
b1000 O
1R
1U
0V
0Y
0Z
0]
1^
1a
b1001 b
1e
b1000 f
1i
1D"
1H"
1##
1'#
1_#
#131000
#135000
0#
0-
0e
0i
0D"
0H"
0##
0'#
0_#
#140000
1#
b1001 $
b00011 )
b0000000000001001 *
1-
b1001 .
1/
b0000 0
b1001 1
b1010 2
13
b1001 6
b1010 8
b00010 :
1<
0>
1?
1@
1C
b1001 O
1Q
0R
1T
0U
1V
1X
1\
1`
0a
b0000 b
1e
b1001 f
1g
1i
1B"
1D"
1H"
1##
1'#
1_#
#141000
#145000
0#
0-
0e
0i
0D"
0H"
0##
0'#
0_#
