Guia_TP/CLP_CESE/CLP_CESE.srcs/sources_1/new/ffd.vhd
----------------------------------------------------------------------------------
-- Company: 
-- Engineer: 
-- 
-- Create Date: 27.08.2026 20:49:25
-- Design Name: 
-- Module Name: ffd - Behavioral
-- Project Name: 
-- Target Devices: 
-- Tool Versions: 
-- Description: Flip-flop D con enable y reset sincrono activos en alto.
-- 
-- Dependencies: 
-- 
-- Revision:
-- Revision 0.01 - File Created
-- Additional Comments:
-- 
----------------------------------------------------------------------------------


library IEEE;
use IEEE.STD_LOGIC_1164.ALL;

-- Uncomment the following library declaration if using
-- arithmetic functions with Signed or Unsigned values
--use IEEE.NUMERIC_STD.ALL;

-- Uncomment the following library declaration if instantiating
-- any Xilinx leaf cells in this code.
--library UNISIM;
--use UNISIM.VComponents.all;

entity ffd is
    Port ( d : in STD_LOGIC;
           ena : in STD_LOGIC;
           rst : in STD_LOGIC;
           clk : in STD_LOGIC;
           q : out STD_LOGIC);
end ffd;

architecture Behavioral of ffd is

begin
    
    process(clk)
    begin
        if rising_edge(clk) then
            if rst = '1' then
                q<='0';    
            else
                if ena = '1' then
                    q<=d;
                end if;
            end if;
        end if;
    end process;

end Behavioral;

Guia_TP/CLP_CESE/CLP_CESE.srcs/sources_1/new/celda_unitaria_contador_binario.vhd
----------------------------------------------------------------------------------
-- Company: 
-- Engineer: 
-- 
-- Create Date: 27.08.2026 22:24:13
-- Design Name: 
-- Module Name: celda_unitaria_contador_binario - Behavioral
-- Project Name: 
-- Target Devices: 
-- Tool Versions: 
-- Description: Celda de 1 bit para construir contadores binarios estructurales.
-- 
-- Dependencies: 
-- 
-- Revision:
-- Revision 0.01 - File Created
-- Additional Comments:
-- 
----------------------------------------------------------------------------------


library IEEE;
use IEEE.STD_LOGIC_1164.ALL;

-- Uncomment the following library declaration if using
-- arithmetic functions with Signed or Unsigned values
--use IEEE.NUMERIC_STD.ALL;

-- Uncomment the following library declaration if instantiating
-- any Xilinx leaf cells in this code.
--library UNISIM;
--use UNISIM.VComponents.all;

entity celda_unitaria_contador_binario is
    Port (
        ena_in  : in  STD_LOGIC;
        rst     : in  STD_LOGIC;
        clk     : in  STD_LOGIC;
        q       : out STD_LOGIC;
        ena_out : out STD_LOGIC
    );
end celda_unitaria_contador_binario;

architecture Behavioral of celda_unitaria_contador_binario is

    signal d_aux : STD_LOGIC;
    signal q_aux : STD_LOGIC;

begin

    d_aux   <= q_aux xor ena_in;
    ena_out <= q_aux and ena_in;
    q       <= q_aux;

    ffd_instance : entity work.ffd
        port map (
            d   => d_aux,
            ena => '1',
            rst => rst,
            clk => clk,
            q   => q_aux
        );

end Behavioral;

Guia_TP/CLP_CESE/CLP_CESE.srcs/sources_1/new/contador_binario_N_bits_estructural.vhd
----------------------------------------------------------------------------------
-- Company: 
-- Engineer: 
-- 
-- Create Date: 27.08.2026 22:52:03
-- Design Name: 
-- Module Name: contador_binario_N_bits_estructural - Behavioral
-- Project Name: 
-- Target Devices: 
-- Tool Versions: 
-- Description: Contador binario estructural generico de N bits.
-- 
-- Dependencies: 
-- 
-- Revision:
-- Revision 0.01 - File Created
-- Additional Comments:
-- 
----------------------------------------------------------------------------------


library IEEE;
use IEEE.STD_LOGIC_1164.ALL;

-- Uncomment the following library declaration if using
-- arithmetic functions with Signed or Unsigned values
--use IEEE.NUMERIC_STD.ALL;

-- Uncomment the following library declaration if instantiating
-- any Xilinx leaf cells in this code.
--library UNISIM;
--use UNISIM.VComponents.all;

entity contador_binario_N_bits_estructural is
    Generic (
        N : integer := 4
    );
    Port (
        ena : in  STD_LOGIC;
        rst : in  STD_LOGIC;
        clk : in  STD_LOGIC;
        q   : out STD_LOGIC_VECTOR(N-1 downto 0)
    );
end contador_binario_N_bits_estructural;

architecture Behavioral of contador_binario_N_bits_estructural is

    signal ena_aux : STD_LOGIC_VECTOR(N+1-1 downto 0);

begin

    ena_aux(0) <= ena;

    celdas : for i in 0 to N-1 generate
        celda_instance : entity work.celda_unitaria_contador_binario
            port map (
                ena_in  => ena_aux(i),
                rst     => rst,
                clk     => clk,
                q       => q(i),
                ena_out => ena_aux(i + 1)
            );
    end generate celdas;

end Behavioral;

Guia_TP/cocotb/waveforms/contador_binario_N_bits_estructural.vcd
$date
  Sun Aug 30 19:25:49 2026
$end
$version
  GHDL v0
$end
$timescale
  1 ps
$end
$scope module standard $end
$upscope $end
$scope module textio $end
$upscope $end
$scope module std_logic_1164 $end
$upscope $end
$scope module contador_binario_n_bits_estructural $end
$var reg 1 ! ena $end
$var reg 1 " rst $end
$var reg 1 # clk $end
$var reg 5 $ q[4:0] $end
$var reg 6 % ena_aux[5:0] $end
$scope module celdas(0) $end
$scope module celda_instance $end
$var reg 1 & ena_in $end
$var reg 1 ' rst $end
$var reg 1 ( clk $end
$var reg 1 ) q $end
$var reg 1 * ena_out $end
$var reg 1 + d_aux $end
$var reg 1 , q_aux $end
$scope module ffd_instance $end
$var reg 1 - d $end
$var reg 1 . ena $end
$var reg 1 / rst $end
$var reg 1 0 clk $end
$var reg 1 1 q $end
$upscope $end
$upscope $end
$upscope $end
$scope module celdas(1) $end
$scope module celda_instance $end
$var reg 1 2 ena_in $end
$var reg 1 3 rst $end
$var reg 1 4 clk $end
$var reg 1 5 q $end
$var reg 1 6 ena_out $end
$var reg 1 7 d_aux $end
$var reg 1 8 q_aux $end
$scope module ffd_instance $end
$var reg 1 9 d $end
$var reg 1 : ena $end
$var reg 1 ; rst $end
$var reg 1 < clk $end
$var reg 1 = q $end
$upscope $end
$upscope $end
$upscope $end
$scope module celdas(2) $end
$scope module celda_instance $end
$var reg 1 > ena_in $end
$var reg 1 ? rst $end
$var reg 1 @ clk $end
$var reg 1 A q $end
$var reg 1 B ena_out $end
$var reg 1 C d_aux $end
$var reg 1 D q_aux $end
$scope module ffd_instance $end
$var reg 1 E d $end
$var reg 1 F ena $end
$var reg 1 G rst $end
$var reg 1 H clk $end
$var reg 1 I q $end
$upscope $end
$upscope $end
$upscope $end
$scope module celdas(3) $end
$scope module celda_instance $end
$var reg 1 J ena_in $end
$var reg 1 K rst $end
$var reg 1 L clk $end
$var reg 1 M q $end
$var reg 1 N ena_out $end
$var reg 1 O d_aux $end
$var reg 1 P q_aux $end
$scope module ffd_instance $end
$var reg 1 Q d $end
$var reg 1 R ena $end
$var reg 1 S rst $end
$var reg 1 T clk $end
$var reg 1 U q $end
$upscope $end
$upscope $end
$upscope $end
$scope module celdas(4) $end
$scope module celda_instance $end
$var reg 1 V ena_in $end
$var reg 1 W rst $end
$var reg 1 X clk $end
$var reg 1 Y q $end
$var reg 1 Z ena_out $end
$var reg 1 [ d_aux $end
$var reg 1 \ q_aux $end
$scope module ffd_instance $end
$var reg 1 ] d $end
$var reg 1 ^ ena $end
$var reg 1 _ rst $end
$var reg 1 ` clk $end
$var reg 1 a q $end
$upscope $end
$upscope $end
$upscope $end
$upscope $end
$enddefinitions $end
#0
0!
1"
1#
bUUUUU $
b000000 %
0&
1'
1(
U)
0*
U+
U,
U-
1.
1/
10
U1
02
13
14
U5
06
U7
U8
U9
1:
1;
1<
U=
0>
1?
1@
UA
0B
UC
UD
UE
1F
1G
1H
UI
0J
1K
1L
UM
0N
UO
UP
UQ
1R
1S
1T
UU
0V
1W
1X
UY
0Z
U[
U\
U]
1^
1_
1`
Ua
#5000
0#
0(
00
04
0<
0@
0H
0L
0T
0X
0`
#10000
1#
b00000 $
1(
0)
0+
0,
0-
10
01
14
05
07
08
09
1<
0=
1@
0A
0C
0D
0E
1H
0I
1L
0M
0O
0P
0Q
1T
0U
1X
0Y
0[
0\
0]
1`
0a
#15000
0#
0(
00
04
0<
0@
0H
0L
0T
0X
0`
#20000
1#
1(
10
14
1<
1@
1H
1L
1T
1X
1`
#25000
0#
0(
00
04
0<
0@
0H
0L
0T
0X
0`
#30000
1#
1(
10
14
1<
1@
1H
1L
1T
1X
1`
#35000
0#
0(
00
04
0<
0@
0H
0L
0T
0X
0`
#40000
1#
1(
10
14
1<
1@
1H
1L
1T
1X
1`
#41000
0"
0'
0/
03
0;
0?
0G
0K
0S
0W
0_
#42000
#45000
0#
0(
00
04
0<
0@
0H
0L
0T
0X
0`
#50000
1#
1(
10
14
1<
1@
1H
1L
1T
1X
1`
#51000
1!
b000001 %
1&
1+
1-
#55000
0#
0(
00
04
0<
0@
0H
0L
0T
0X
0`
#60000
1#
b00001 $
b000011 %
1(
1)
1*
0+
1,
0-
10
11
12
14
17
19
1<
1@
1H
1L
1T
1X
1`
#61000
#65000
0#
0(
00
04
0<
0@
0H
0L
0T
0X
0`
#70000
1#
b00010 $
b000001 %
1(
0)
0*
1+
0,
1-
10
01
02
14
15
06
17
18
19
1<
1=
0>
1@
0C
0E
1H
1L
1T
1X
1`
#71000
#75000
0#
0(
00
04
0<
0@
0H
0L
0T
0X
0`
#80000
1#
b00011 $
b000111 %
1(
1)
1*
0+
1,
0-
10
11
12
14
16
07
09
1<
1>
1@
1C
1E
1H
1L
1T
1X
1`
#81000
#85000
0#
0(
00
04
0<
0@
0H
0L
0T
0X
0`
#90000
1#
b00100 $
b000001 %
1(
0)
0*
1+
0,
1-
10
01
02
14
05
06
07
08
09
1<
0=
0>
1@
1A
0B
1C
1D
1E
1H
1I
0J
1L
0O
0Q
1T
1X
1`
#91000
#95000
0#
0(
00
04
0<
0@
0H
0L
0T
0X
0`
#100000
1#
b00101 $
b000011 %
1(
1)
1*
0+
1,
0-
10
11
12
14
17
19
1<
1@
1H
1L
1T
1X
1`
#101000
#105000
0#
0(
00
04
0<
0@
0H
0L
0T
0X
0`
#110000
1#
b00110 $
b000001 %
1(
0)
0*
1+
0,
1-
10
01
02
14
15
06
17
18
19
1<
1=
0>
1@
0B
1C
1E
1H
0J
1L
0O
0Q
1T
1X
1`
#111000
#115000
0#
0(
00
04
0<
0@
0H
0L
0T
0X
0`
#120000
1#
b00111 $
b001111 %
1(
1)
1*
0+
1,
0-
10
11
12
14
16
07
09
1<
1>
1@
1B
0C
0E
1H
1J
1L
1O
1Q
1T
1X
1`
#121000
#125000
0#
0(
00
04
0<
0@
0H
0L
0T
0X
0`
#130000
1#
b01000 $
b000001 %
1(
0)
0*
1+
0,
1-
10
01
02
14
05
06
07
08
09
1<
0=
0>
1@
0A
0B
0C
0D
0E
1H
0I
0J
1L
1M
0N
1O
1P
1Q
1T
1U
0V
1X
0[
0]
1`
#131000
#135000
0#
0(
00
04
0<
0@
0H
0L
0T
0X
0`
#140000
1#
b01001 $
b000011 %
1(
1)
1*
0+
1,
0-
10
11
12
14
17
19
1<
1@
1H
1L
1T
1X
1`
#141000
#145000
0#
0(
00
04
0<
0@
0H
0L
0T
0X
0`
#150000
1#
b01010 $
b000001 %
1(
0)
0*
1+
0,
1-
10
01
02
14
15
06
17
18
19
1<
1=
0>
1@
0C
0E
1H
1L
1T
1X
1`
#151000
#155000
0#
0(
00
04
0<
0@
0H
0L
0T
0X
0`
#160000
1#
b01011 $
b000111 %
1(
1)
1*
0+
1,
0-
10
11
12
14
16
07
09
1<
1>
1@
1C
1E
1H
1L
1T
1X
1`
#161000
#165000
0#
0(
00
04
0<
0@
0H
0L
0T
0X
0`
#170000
1#
b01100 $
b000001 %
1(
0)
0*
1+
0,
1-
10
01
02
14
05
06
07
08
09
1<
0=
0>
1@
1A
0B
1C
1D
1E
1H
1I
0J
1L
0N
1O
1Q
1T
0V
1X
0[
0]
1`
#171000
#175000
0#
0(
00
04
0<
0@
0H
0L
0T
0X
0`
#180000
1#
b01101 $
b000011 %
1(
1)
1*
0+
1,
0-
10
11
12
14
17
19
1<
1@
1H
1L
1T
1X
1`
#181000
#185000
0#
0(
00
04
0<
0@
0H
0L
0T
0X
0`
#190000
1#
b01110 $
b000001 %
1(
0)
0*
1+
0,
1-
10
01
02
14
15
06
17
18
19
1<
1=
0>
1@
0B
1C
1E
1H
0J
1L
0N
1O
1Q
1T
0V
1X
0[
0]
1`
#191000
#195000
0#
0(
00
04
0<
0@
0H
0L
0T
0X
0`
#200000
1#
b01111 $
b011111 %
1(
1)
1*
0+
1,
0-
10
11
12
14
16
07
09
1<
1>
1@
1B
0C
0E
1H
1J
1L
1N
0O
0Q
1T
1V
1X
1[
1]
1`
#201000
#205000
0#
0(
00
04
0<
0@
0H
0L
0T
0X
0`
#210000
1#
b10000 $
b000001 %
1(
0)
0*
1+
0,
1-
10
01
02
14
05
06
07
08
09
1<
0=
0>
1@
0A
0B
0C
0D
0E
1H
0I
0J
1L
0M
0N
0O
0P
0Q
1T
0U
0V
1X
1Y
0Z
1[
1\
1]
1`
1a
#211000
#215000
0#
0(
00
04
0<
0@
0H
0L
0T
0X
0`
#220000
1#
b10001 $
b000011 %
1(
1)
1*
0+
1,
0-
10
11
12
14
17
19
1<
1@
1H
1L
1T
1X
1`
#221000
#225000
0#
0(
00
04
0<
0@
0H
0L
0T
0X
0`
#230000
1#
b10010 $
b000001 %
1(
0)
0*
1+
0,
1-
10
01
02
14
15
06
17
18
19
1<
1=
0>
1@
0C
0E
1H
1L
1T
1X
1`
#231000
#235000
0#
0(
00
04
0<
0@
0H
0L
0T
0X
0`
#240000
1#
b10011 $
b000111 %
1(
1)
1*
0+
1,
0-
10
11
12
14
16
07
09
1<
1>
1@
1C
1E
1H
1L
1T
1X
1`
#241000
#245000
0#
0(
00
04
0<
0@
0H
0L
0T
0X
0`
#250000
1#
b10100 $
b000001 %
1(
0)
0*
1+
0,
1-
10
01
02
14
05
06
07
08
09
1<
0=
0>
1@
1A
0B
1C
1D
1E
1H
1I
0J
1L
0O
0Q
1T
1X
1`
#251000
#255000
0#
0(
00
04
0<
0@
0H
0L
0T
0X
0`
#260000
1#
b10101 $
b000011 %
1(
1)
1*
0+
1,
0-
10
11
12
14
17
19
1<
1@
1H
1L
1T
1X
1`
#261000
#265000
0#
0(
00
04
0<
0@
0H
0L
0T
0X
0`
#270000
1#
b10110 $
b000001 %
1(
0)
0*
1+
0,
1-
10
01
02
14
15
06
17
18
19
1<
1=
0>
1@
0B
1C
1E
1H
0J
1L
0O
0Q
1T
1X
1`
#271000
#275000
0#
0(
00
04
0<
0@
0H
0L
0T
0X
0`
#280000
1#
b10111 $
b001111 %
1(
1)
1*
0+
1,
0-
10
11
12
14
16
07
09
1<
1>
1@
1B
0C
0E
1H
1J
1L
1O
1Q
1T
1X
1`
#281000
#285000
0#
0(
00
04
0<
0@
0H
0L
0T
0X
0`
#290000
1#
b11000 $
b000001 %
1(
0)
0*
1+
0,
1-
10
01
02
14
05
06
07
08
09
1<
0=
0>
1@
0A
0B
0C
0D
0E
1H
0I
0J
1L
1M
0N
1O
1P
1Q
1T
1U
0V
1X
0Z
1[
1]
1`
#291000
#295000
0#
0(
00
04
0<
0@
0H
0L
0T
0X
0`
#300000
1#
b11001 $
b000011 %
1(
1)
1*
0+
1,
0-
10
11
12
14
17
19
1<
1@
1H
1L
1T
1X
1`
#301000
#305000
0#
0(
00
04
0<
0@
0H
0L
0T
0X
0`
#310000
1#
b11010 $
b000001 %
1(
0)
0*
1+
0,
1-
10
01
02
14
15
06
17
18
19
1<
1=
0>
1@
0C
0E
1H
1L
1T
1X
1`
#311000
#315000
0#
0(
00
04
0<
0@
0H
0L
0T
0X
0`
#320000
1#
b11011 $
b000111 %
1(
1)
1*
0+
1,
0-
10
11
12
14
16
07
09
1<
1>
1@
1C
1E
1H
1L
1T
1X
1`
#321000
#325000
0#
0(
00
04
0<
0@
0H
0L
0T
0X
0`
#330000
1#
b11100 $
b000001 %
1(
0)
0*
1+
0,
1-
10
01
02
14
05
06
07
08
09
1<
0=
0>
1@
1A
0B
1C
1D
1E
1H
1I
0J
1L
0N
1O
1Q
1T
0V
1X
0Z
1[
1]
1`
#331000
#335000
0#
0(
00
04
0<
0@
0H
0L
0T
0X
0`
#340000
1#
b11101 $
b000011 %
1(
1)
1*
0+
1,
0-
10
11
12
14
17
19
1<
1@
1H
1L
1T
1X
1`
#341000
#345000
0#
0(
00
04
0<
0@
0H
0L
0T
0X
0`
#350000
1#
b11110 $
b000001 %
1(
0)
0*
1+
0,
1-
10
01
02
14
15
06
17
18
19
1<
1=
0>
1@
0B
1C
1E
1H
0J
1L
0N
1O
1Q
1T
0V
1X
0Z
1[
1]
1`
#351000
#355000
0#
0(
00
04
0<
0@
0H
0L
0T
0X
0`
#360000
1#
b11111 $
b111111 %
1(
1)
1*
0+
1,
0-
10
11
12
14
16
07
09
1<
1>
1@
1B
0C
0E
1H
1J
1L
1N
0O
0Q
1T
1V
1X
1Z
0[
0]
1`
#361000
#365000
0#
0(
00
04
0<
0@
0H
0L
0T
0X
0`
#370000
1#
b00000 $
b000001 %
1(
0)
0*
1+
0,
1-
10
01
02
14
05
06
07
08
09
1<
0=
0>
1@
0A
0B
0C
0D
0E
1H
0I
0J
1L
0M
0N
0O
0P
0Q
1T
0U
0V
1X
0Y
0Z
0[
0\
0]
1`
0a
#371000
0!
b000000 %
0&
0+
0-
#375000
0#
0(
00
04
0<
0@
0H
0L
0T
0X
0`
#380000
1#
1(
10
14
1<
1@
1H
1L
1T
1X
1`
#381000
1!
b000001 %
1&
1+
1-
#385000
0#
0(
00
04
0<
0@
0H
0L
0T
0X
0`
#390000
1#
b00001 $
b000011 %
1(
1)
1*
0+
1,
0-
10
11
12
14
17
19
1<
1@
1H
1L
1T
1X
1`
#391000
#395000
0#
0(
00
04
0<
0@
0H
0L
0T
0X
0`
#400000
1#
b00010 $
b000001 %
1(
0)
0*
1+
0,
1-
10
01
02
14
15
06
17
18
19
1<
1=
0>
1@
0C
0E
1H
1L
1T
1X
1`
#405000
0#
0(
00
04
0<
0@
0H
0L
0T
0X
0`
#410000
1#
b00011 $
b000111 %
1(
1)
1*
0+
1,
0-
10
11
12
14
16
07
09
1<
1>
1@
1C
1E
1H
1L
1T
1X
1`
#415000
0#
0(
00
04
0<
0@
0H
0L
0T
0X
0`
#420000
1#
b00100 $
b000001 %
1(
0)
0*
1+
0,
1-
10
01
02
14
05
06
07
08
09
1<
0=
0>
1@
1A
0B
1C
1D
1E
1H
1I
0J
1L
0O
0Q
1T
1X
1`
#425000
0#
0(
00
04
0<
0@
0H
0L
0T
0X
0`
#430000
1#
b00101 $
b000011 %
1(
1)
1*
0+
1,
0-
10
11
12
14
17
19
1<
1@
1H
1L
1T
1X
1`
#435000
0#
0(
00
04
0<
0@
0H
0L
0T
0X
0`
#440000
1#
b00110 $
b000001 %
1(
0)
0*
1+
0,
1-
10
01
02
14
15
06
17
18
19
1<
1=
0>
1@
0B
1C
1E
1H
0J
1L
0O
0Q
1T
1X
1`
#445000
0#
0(
00
04
0<
0@
0H
0L
0T
0X
0`
#450000
1#
b00111 $
b001111 %
1(
1)
1*
0+
1,
0-
10
11
12
14
16
07
09
1<
1>
1@
1B
0C
0E
1H
1J
1L
1O
1Q
1T
1X
1`
#455000
0#
0(
00
04
0<
0@
0H
0L
0T
0X
0`
#460000
1#
b01000 $
b000001 %
1(
0)
0*
1+
0,
1-
10
01
02
14
05
06
07
08
09
1<
0=
0>
1@
0A
0B
0C
0D
0E
1H
0I
0J
1L
1M
0N
1O
1P
1Q
1T
1U
0V
1X
0[
0]
1`
#465000
0#
0(
00
04
0<
0@
0H
0L
0T
0X
0`
#470000
1#
b01001 $
b000011 %
1(
1)
1*
0+
1,
0-
10
11
12
14
17
19
1<
1@
1H
1L
1T
1X
1`
#475000
0#
0(
00
04
0<
0@
0H
0L
0T
0X
0`
#480000
1#
b01010 $
b000001 %
1(
0)
0*
1+
0,
1-
10
01
02
14
15
06
17
18
19
1<
1=
0>
1@
0C
0E
1H
1L
1T
1X
1`
#485000
0#
0(
00
04
0<
0@
0H
0L
0T
0X
0`
#490000
1#
b01011 $
b000111 %
1(
1)
1*
0+
1,
0-
10
11
12
14
16
07
09
1<
1>
1@
1C
1E
1H
1L
1T
1X
1`
