Guia_TP/CLP_CESE/CLP_CESE.srcs/sources_1/new/registro_N_bits.vhd
----------------------------------------------------------------------------------
-- Company: 
-- Engineer: 
-- 
-- Create Date: 27.08.2026 23:34:00
-- Design Name: 
-- Module Name: registro_N_bits - Behavioral
-- Project Name: 
-- Target Devices: 
-- Tool Versions: 
-- Description: Registro paralelo generico de N bits con enable y reset sincrono.
-- 
-- Dependencies: 
-- 
-- Revision:
-- Revision 0.01 - File Created
-- Additional Comments:
-- 
----------------------------------------------------------------------------------


library IEEE;
use IEEE.STD_LOGIC_1164.ALL;

-- Uncomment the following library declaration if using
-- arithmetic functions with Signed or Unsigned values
--use IEEE.NUMERIC_STD.ALL;

-- Uncomment the following library declaration if instantiating
-- any Xilinx leaf cells in this code.
--library UNISIM;
--use UNISIM.VComponents.all;

entity registro_N_bits is
    Generic (
        N : integer := 4
    );
    Port (
        d   : in  STD_LOGIC_VECTOR(N-1 downto 0);
        ena : in  STD_LOGIC;
        rst : in  STD_LOGIC;
        clk : in  STD_LOGIC;
        q   : out STD_LOGIC_VECTOR(N-1 downto 0)
    );
end registro_N_bits;

architecture Behavioral of registro_N_bits is

begin

    process(clk)
    begin
        if rising_edge(clk) then
            if rst = '1' then
                q <= (others => '0');
            elsif ena = '1' then
                q <= d;
            end if;
        end if;
    end process;

end Behavioral;

Guia_TP/CLP_CESE/CLP_CESE.srcs/sources_1/new/mux_2_a_1.vhd
----------------------------------------------------------------------------------
-- Company: 
-- Engineer: 
-- 
-- Create Date: 27.08.2026 20:36:34
-- Design Name: 
-- Module Name: mux_2_a_1 - Behavioral
-- Project Name: 
-- Target Devices: 
-- Tool Versions: 
-- Description: Multiplexor combinacional de dos entradas de 1 bit.
-- 
-- Dependencies: 
-- 
-- Revision:
-- Revision 0.01 - File Created
-- Additional Comments:
-- 
----------------------------------------------------------------------------------


library IEEE;
use IEEE.STD_LOGIC_1164.ALL;

-- Uncomment the following library declaration if using
-- arithmetic functions with Signed or Unsigned values
--use IEEE.NUMERIC_STD.ALL;

-- Uncomment the following library declaration if instantiating
-- any Xilinx leaf cells in this code.
--library UNISIM;
--use UNISIM.VComponents.all;

entity mux_2_a_1 is
    Port (  a : in STD_LOGIC;
            b : in STD_LOGIC;
           sel: in STD_LOGIC;
           mux: out STD_LOGIC);
end mux_2_a_1;

architecture Behavioral of mux_2_a_1 is

begin
    mux<= a when sel='0' else b;
end Behavioral;

Guia_TP/CLP_CESE/CLP_CESE.srcs/sources_1/new/comparador_igual.vhd
----------------------------------------------------------------------------------
-- Company: 
-- Engineer: 
-- 
-- Create Date: 27.08.2026 23:27:44
-- Design Name: 
-- Module Name: comparador_igual - Behavioral
-- Project Name: 
-- Target Devices: 
-- Tool Versions: 
-- Description: Comparador de igualdad generico para dos palabras de N bits.
-- 
-- Dependencies: 
-- 
-- Revision:
-- Revision 0.01 - File Created
-- Additional Comments:
-- 
----------------------------------------------------------------------------------


library IEEE;
use IEEE.STD_LOGIC_1164.ALL;

-- Uncomment the following library declaration if using
-- arithmetic functions with Signed or Unsigned values
--use IEEE.NUMERIC_STD.ALL;

-- Uncomment the following library declaration if instantiating
-- any Xilinx leaf cells in this code.
--library UNISIM;
--use UNISIM.VComponents.all;

entity comparador_igual is
    Generic (
        N : integer := 4
    );
    Port ( a     : in  STD_LOGIC_VECTOR(N-1 downto 0);
           b     : in  STD_LOGIC_VECTOR(N-1 downto 0);
           igual : out STD_LOGIC
    );
end comparador_igual;

architecture Behavioral of comparador_igual is

begin
    igual <= '1' when a = b else '0';

end Behavioral;

Guia_TP/CLP_CESE/CLP_CESE.srcs/sources_1/new/adder_1_bit.vhd
----------------------------------------------------------------------------------
-- Company: 
-- Engineer: 
-- 
-- Create Date: 27.08.2026 19:23:36
-- Design Name: 
-- Module Name: adder_1_bit - Behavioral
-- Project Name: 
-- Target Devices: 
-- Tool Versions: 
-- Description: Sumador completo de 1 bit con acarreo de entrada y salida.
-- 
-- Dependencies: 
-- 
-- Revision:
-- Revision 0.01 - File Created
-- Additional Comments:
-- 
----------------------------------------------------------------------------------


library IEEE;
use IEEE.STD_LOGIC_1164.ALL;

-- Uncomment the following library declaration if using
-- arithmetic functions with Signed or Unsigned values
--use IEEE.NUMERIC_STD.ALL;

-- Uncomment the following library declaration if instantiating
-- any Xilinx leaf cells in this code.
--library UNISIM;
--use UNISIM.VComponents.all;

entity adder_1_bit is
    Port ( ci : in STD_LOGIC;
           a : in STD_LOGIC;
           b : in STD_LOGIC;
           s : out STD_LOGIC;
           co : out STD_LOGIC);
end adder_1_bit;

architecture Behavioral of adder_1_bit is

begin
    
    s<= a xor b xor ci;
    co<= (a and b) or (b and ci) or (a and ci);

end Behavioral;

Guia_TP/CLP_CESE/CLP_CESE.srcs/sources_1/new/adder_4_bits.vhd
----------------------------------------------------------------------------------
-- Company: 
-- Engineer: 
-- 
-- Create Date: 27.08.2026 19:49:11
-- Design Name: 
-- Module Name: adder_4_bits - Behavioral
-- Project Name: 
-- Target Devices: 
-- Tool Versions: 
-- Description: Sumador estructural de 4 bits formado por cuatro sumadores completos.
-- 
-- Dependencies: 
-- 
-- Revision:
-- Revision 0.01 - File Created
-- Additional Comments:
-- 
----------------------------------------------------------------------------------


library IEEE;
use IEEE.STD_LOGIC_1164.ALL;

library work;
use work.adder_1_bit;
-- Uncomment the following library declaration if using
-- arithmetic functions with Signed or Unsigned values
--use IEEE.NUMERIC_STD.ALL;

-- Uncomment the following library declaration if instantiating
-- any Xilinx leaf cells in this code.
--library UNISIM;
--use UNISIM.VComponents.all;

entity adder_4_bits is
    Port ( ci : in STD_LOGIC;
            a : in STD_LOGIC_VECTOR(4-1 downto 0);
            b : in STD_LOGIC_VECTOR(4-1 downto 0);
            s : out STD_LOGIC_VECTOR(4-1 downto 0);
           co : out STD_LOGIC);
end adder_4_bits;

architecture Behavioral of adder_4_bits is
    signal c_vector : STD_LOGIC_VECTOR(5-1 downto 0);
begin
    c_vector(0) <= ci;
    co <= c_vector(4);

    ciclo : for i in 0 to 3 generate
        adder_1_bit_instance : entity work.adder_1_bit
            port map (
                ci => c_vector(i),
                a  => a(i),
                b  => b(i),
                s  => s(i),
                co => c_vector(i + 1)
            );
    end generate ciclo;
end Behavioral;

Guia_TP/CLP_CESE/CLP_CESE.srcs/sources_1/new/contador_bcd.vhd
----------------------------------------------------------------------------------
-- Company: 
-- Engineer: 
-- 
-- Create Date: 27.08.2026 23:14:29
-- Design Name: 
-- Module Name: contador_bcd - Behavioral
-- Project Name: 
-- Target Devices: 
-- Tool Versions: 
-- Description: Contador BCD estructural de un digito con enable y acarreo.
-- 
-- Dependencies: 
-- 
-- Revision:
-- Revision 0.01 - File Created
-- Additional Comments:
-- 
----------------------------------------------------------------------------------


library IEEE;
use IEEE.STD_LOGIC_1164.ALL;

-- Uncomment the following library declaration if using
-- arithmetic functions with Signed or Unsigned values
--use IEEE.NUMERIC_STD.ALL;

-- Uncomment the following library declaration if instantiating
-- any Xilinx leaf cells in this code.
--library UNISIM;
--use UNISIM.VComponents.all;

entity contador_bcd is
    Port ( ena : in  STD_LOGIC;
           rst : in  STD_LOGIC;
           clk : in  STD_LOGIC;
           q   : out STD_LOGIC_VECTOR(4-1 downto 0);
           co  : out STD_LOGIC);
end contador_bcd;

architecture Behavioral of contador_bcd is

    signal d_reg  : STD_LOGIC_VECTOR(3 downto 0);
    signal q_reg  : STD_LOGIC_VECTOR(3 downto 0);
    signal q_inc  : STD_LOGIC_VECTOR(3 downto 0);
    signal igual9 : STD_LOGIC;
    signal co_aux : STD_LOGIC;

begin

    q <= q_reg;
    co <= ena and igual9;

    adder_instance : entity work.adder_4_bits
        port map (
            ci => '0',
            a  => q_reg,
            b  => "0001",
            s  => q_inc,
            co => co_aux
        );

    comparador_instance : entity work.comparador_igual
        generic map (
            N => 4
        )
        port map (
            a     => q_reg,
            b     => "1001",
            igual => igual9
        );

    -- Cuando el valor actual es 9, el siguiente valor debe ser 0.
    mux_bcd : for i in 0 to 3 generate
        mux_instance : entity work.mux_2_a_1
            port map (
                a   => q_inc(i),
                b   => '0',
                sel => igual9,
                mux => d_reg(i)
            );
    end generate mux_bcd;

    registro_instance : entity work.registro_N_bits
        generic map (
            N => 4
        )
        port map (
            d   => d_reg,
            ena => ena,
            rst => rst,
            clk => clk,
            q   => q_reg
        );

end Behavioral;

Guia_TP/CLP_CESE/CLP_CESE.srcs/sources_1/new/contador_N_clk.vhd
----------------------------------------------------------------------------------
-- Company: 
-- Engineer: 
-- 
-- Create Date: 28.08.2026 00:12:55
-- Design Name: 
-- Module Name: contador_N_clk - Behavioral
-- Project Name: 
-- Target Devices: 
-- Tool Versions: 
-- Description: Generador de un pulso de habilitacion cada N ciclos de reloj.
-- 
-- Dependencies: 
-- 
-- Revision:
-- Revision 0.01 - File Created
-- Additional Comments:
-- 
----------------------------------------------------------------------------------


library IEEE;
use IEEE.STD_LOGIC_1164.ALL;
use IEEE.NUMERIC_STD.ALL;
use IEEE.MATH_REAL.ALL;

-- Uncomment the following library declaration if using
-- arithmetic functions with Signed or Unsigned values
--use IEEE.NUMERIC_STD.ALL;

-- Uncomment the following library declaration if instantiating
-- any Xilinx leaf cells in this code.
--library UNISIM;
--use UNISIM.VComponents.all;

entity contador_N_clk is
    Generic (
        N : integer := 5
    );
    Port (
        rst : in  STD_LOGIC;
        clk : in  STD_LOGIC;
        s   : out STD_LOGIC
    );
end contador_N_clk;

architecture Behavioral of contador_N_clk is
    -- calculo dinamico de la cantidad de bits necesarios para contar hasta N-1
    constant M : integer := integer(ceil(log2(real(N))));
    signal q : unsigned(M-1 downto 0);

begin

    assert (N > 1)
        report "N debe ser mayor que 1"
        severity failure;

    s <= '1' when q = to_unsigned(N-1, M) else '0';

    process(clk)
    begin
        if rising_edge(clk) then
            if rst = '1' then
                q <= to_unsigned(0, M);
            elsif q = to_unsigned(N-1, M) then
                q <= to_unsigned(0, M);
            else
                q <= q + to_unsigned(1, M);
            end if;
        end if;
    end process;

end Behavioral;

Guia_TP/CLP_CESE/CLP_CESE.srcs/sources_1/new/contador_bcd_1_seg.vhd
----------------------------------------------------------------------------------
-- Company: 
-- Engineer: 
-- 
-- Create Date: 28.08.2026 00:32:06
-- Design Name: 
-- Module Name: contador_bcd_1_seg - Behavioral
-- Project Name: 
-- Target Devices: 
-- Tool Versions: 
-- Description: Top level de contador BCD con avance periodico y enable general.
-- 
-- Dependencies: 
-- 
-- Revision:
-- Revision 0.01 - File Created
-- Additional Comments:
-- 
----------------------------------------------------------------------------------


library IEEE;
use IEEE.STD_LOGIC_1164.ALL;

-- Uncomment the following library declaration if using
-- arithmetic functions with Signed or Unsigned values
--use IEEE.NUMERIC_STD.ALL;

-- Uncomment the following library declaration if instantiating
-- any Xilinx leaf cells in this code.
--library UNISIM;
--use UNISIM.VComponents.all;

entity contador_bcd_1_seg is
    Generic (
        SYS_CLK : integer := 100000000
    );
    Port (
        ena : in  STD_LOGIC;
        rst : in  STD_LOGIC;
        clk : in  STD_LOGIC;
        q   : out STD_LOGIC_VECTOR(3 downto 0)
    );
end contador_bcd_1_seg;

architecture Behavioral of contador_bcd_1_seg is

    signal pulso_1s : STD_LOGIC;
    signal ena_bcd  : STD_LOGIC;

begin

    ena_bcd <= ena and pulso_1s;

    generador_1s_instance : entity work.contador_N_clk
        generic map (
            N => SYS_CLK
        )
        port map (
            rst => rst,
            clk => clk,
            s   => pulso_1s
        );

    contador_bcd_instance : entity work.contador_bcd
        port map (
            ena => ena_bcd,
            rst => rst,
            clk => clk,
            q   => q,
            co  => open
        );

end Behavioral;

Guia_TP/cocotb/waveforms/contador_bcd_1_seg.vcd
$date
  Sun Aug 30 19:25:17 2026
$end
$version
  GHDL v0
$end
$timescale
  1 ps
$end
$scope module standard $end
$upscope $end
$scope module textio $end
$upscope $end
$scope module std_logic_1164 $end
$upscope $end
$scope module numeric_std $end
$upscope $end
$scope module math_real $end
$upscope $end
$scope module contador_bcd_1_seg $end
$var reg 1 ! ena $end
$var reg 1 " rst $end
$var reg 1 # clk $end
$var reg 4 $ q[3:0] $end
$var reg 1 % pulso_1s $end
$var reg 1 & ena_bcd $end
$scope module generador_1s_instance $end
$var reg 1 ' rst $end
$var reg 1 ( clk $end
$var reg 1 ) s $end
$var reg 3 * q[2:0] $end
$upscope $end
$scope module contador_bcd_instance $end
$var reg 1 + ena $end
$var reg 1 , rst $end
$var reg 1 - clk $end
$var reg 4 . q[3:0] $end
$var reg 1 / co $end
$var reg 4 0 d_reg[3:0] $end
$var reg 4 1 q_reg[3:0] $end
$var reg 4 2 q_inc[3:0] $end
$var reg 1 3 igual9 $end
$var reg 1 4 co_aux $end
$scope module adder_instance $end
$var reg 1 5 ci $end
$var reg 4 6 a[3:0] $end
$var reg 4 7 b[3:0] $end
$var reg 4 8 s[3:0] $end
$var reg 1 9 co $end
$var reg 5 : c_vector[4:0] $end
$scope module ciclo(0) $end
$scope module adder_1_bit_instance $end
$var reg 1 ; ci $end
$var reg 1 < a $end
$var reg 1 = b $end
$var reg 1 > s $end
$var reg 1 ? co $end
$upscope $end
$upscope $end
$scope module ciclo(1) $end
$scope module adder_1_bit_instance $end
$var reg 1 @ ci $end
$var reg 1 A a $end
$var reg 1 B b $end
$var reg 1 C s $end
$var reg 1 D co $end
$upscope $end
$upscope $end
$scope module ciclo(2) $end
$scope module adder_1_bit_instance $end
$var reg 1 E ci $end
$var reg 1 F a $end
$var reg 1 G b $end
$var reg 1 H s $end
$var reg 1 I co $end
$upscope $end
$upscope $end
$scope module ciclo(3) $end
$scope module adder_1_bit_instance $end
$var reg 1 J ci $end
$var reg 1 K a $end
$var reg 1 L b $end
$var reg 1 M s $end
$var reg 1 N co $end
$upscope $end
$upscope $end
$upscope $end
$scope module comparador_instance $end
$var reg 4 O a[3:0] $end
$var reg 4 P b[3:0] $end
$var reg 1 Q igual $end
$upscope $end
$scope module mux_bcd(0) $end
$scope module mux_instance $end
$var reg 1 R a $end
$var reg 1 S b $end
$var reg 1 T sel $end
$var reg 1 U mux $end
$upscope $end
$upscope $end
$scope module mux_bcd(1) $end
$scope module mux_instance $end
$var reg 1 V a $end
$var reg 1 W b $end
$var reg 1 X sel $end
$var reg 1 Y mux $end
$upscope $end
$upscope $end
$scope module mux_bcd(2) $end
$scope module mux_instance $end
$var reg 1 Z a $end
$var reg 1 [ b $end
$var reg 1 \ sel $end
$var reg 1 ] mux $end
$upscope $end
$upscope $end
$scope module mux_bcd(3) $end
$scope module mux_instance $end
$var reg 1 ^ a $end
$var reg 1 _ b $end
$var reg 1 ` sel $end
$var reg 1 a mux $end
$upscope $end
$upscope $end
$scope module registro_instance $end
$var reg 4 b d[3:0] $end
$var reg 1 c ena $end
$var reg 1 d rst $end
$var reg 1 e clk $end
$var reg 4 f q[3:0] $end
$upscope $end
$upscope $end
$upscope $end
$enddefinitions $end
#0
0!
1"
1#
bUUUU $
0%
0&
1'
1(
0)
bUUU *
0+
1,
1-
bUUUU .
0/
bUUUU 0
bUUUU 1
bUUUU 2
03
U4
05
bUUUU 6
b0001 7
bUUUU 8
U9
bUUUU0 :
0;
U<
1=
U>
U?
U@
UA
0B
UC
UD
UE
UF
0G
UH
UI
UJ
UK
0L
UM
UN
bUUUU O
b1001 P
0Q
UR
0S
0T
UU
UV
0W
0X
UY
UZ
0[
0\
U]
U^
0_
0`
Ua
bUUUU b
0c
1d
1e
bUUUU f
#5000
0#
0(
0-
0e
#10000
1#
b0000 $
1(
b000 *
1-
b0000 .
b0001 0
b0000 1
b0001 2
04
b0000 6
b0001 8
09
b00000 :
0<
1>
0?
0@
0A
0C
0D
0E
0F
0H
0I
0J
0K
0M
0N
b0000 O
1R
1U
0V
0Y
0Z
0]
0^
0a
b0001 b
1e
b0000 f
#15000
0#
0(
0-
0e
#20000
1#
1(
1-
1e
#25000
0#
0(
0-
0e
#30000
1#
1(
1-
1e
#35000
0#
0(
0-
0e
#40000
1#
1(
1-
1e
#41000
0"
0'
0,
0d
#42000
#45000
0#
0(
0-
0e
#50000
1#
1(
b001 *
1-
1e
#55000
0#
0(
0-
0e
#60000
1#
1(
b010 *
1-
1e
#65000
0#
0(
0-
0e
#70000
1#
1(
b011 *
1-
1e
#75000
0#
0(
0-
0e
#80000
1#
1%
1(
1)
b100 *
1-
1e
#85000
0#
0(
0-
0e
#90000
1#
0%
1(
0)
b000 *
1-
1e
#91000
1!
#95000
0#
0(
0-
0e
#100000
1#
1(
b001 *
1-
1e
#105000
0#
0(
0-
0e
#110000
1#
1(
b010 *
1-
1e
#115000
0#
0(
0-
0e
#120000
1#
1(
b011 *
1-
1e
#125000
0#
0(
0-
0e
#130000
1#
1%
1&
1(
1)
b100 *
1+
1-
1c
1e
#135000
0#
0(
0-
0e
#140000
1#
b0001 $
0%
0&
1(
0)
b000 *
0+
1-
b0001 .
b0010 0
b0001 1
b0010 2
b0001 6
b0010 8
b00010 :
1<
0>
1?
1@
1C
b0001 O
0R
0U
1V
1Y
b0010 b
0c
1e
b0001 f
#141000
#145000
0#
0(
0-
0e
#150000
1#
1(
b001 *
1-
1e
#155000
0#
0(
0-
0e
#160000
1#
1(
b010 *
1-
1e
#165000
0#
0(
0-
0e
#170000
1#
1(
b011 *
1-
1e
#175000
0#
0(
0-
0e
#180000
1#
1%
1&
1(
1)
b100 *
1+
1-
1c
1e
#185000
0#
0(
0-
0e
#190000
1#
b0010 $
0%
0&
1(
0)
b000 *
0+
1-
b0010 .
b0011 0
b0010 1
b0011 2
b0010 6
b0011 8
b00000 :
0<
1>
0?
0@
1A
1C
0D
0E
0H
b0010 O
1R
1U
1V
1Y
0Z
0]
b0011 b
0c
1e
b0010 f
#191000
#195000
0#
0(
0-
0e
#200000
1#
1(
b001 *
1-
1e
#205000
0#
0(
0-
0e
#210000
1#
1(
b010 *
1-
1e
#215000
0#
0(
0-
0e
#220000
1#
1(
b011 *
1-
1e
#225000
0#
0(
0-
0e
#230000
1#
1%
1&
1(
1)
b100 *
1+
1-
1c
1e
#235000
0#
0(
0-
0e
#240000
1#
b0011 $
0%
0&
1(
0)
b000 *
0+
1-
b0011 .
b0100 0
b0011 1
b0100 2
b0011 6
b0100 8
b00110 :
1<
0>
1?
1@
0C
1D
1E
1H
b0011 O
0R
0U
0V
0Y
1Z
1]
b0100 b
0c
1e
b0011 f
#241000
#245000
0#
0(
0-
0e
#250000
1#
1(
b001 *
1-
1e
#255000
0#
0(
0-
0e
#260000
1#
1(
b010 *
1-
1e
#265000
0#
0(
0-
0e
#270000
1#
1(
b011 *
1-
1e
#275000
0#
0(
0-
0e
#280000
1#
1%
1&
1(
1)
b100 *
1+
1-
1c
1e
#285000
0#
0(
0-
0e
#290000
1#
b0100 $
0%
0&
1(
0)
b000 *
0+
1-
b0100 .
b0101 0
b0100 1
b0101 2
b0100 6
b0101 8
b00000 :
0<
1>
0?
0@
0A
0C
0D
0E
1F
1H
0I
0J
0M
b0100 O
1R
1U
0V
0Y
1Z
1]
0^
0a
b0101 b
0c
1e
b0100 f
#291000
#295000
0#
0(
0-
0e
#300000
1#
1(
b001 *
1-
1e
#305000
0#
0(
0-
0e
#310000
1#
1(
b010 *
1-
1e
#315000
0#
0(
0-
0e
#320000
1#
1(
b011 *
1-
1e
#325000
0#
0(
0-
0e
#330000
1#
1%
1&
1(
1)
b100 *
1+
1-
1c
1e
#335000
0#
0(
0-
0e
#340000
1#
b0101 $
0%
0&
1(
0)
b000 *
0+
1-
b0101 .
b0110 0
b0101 1
b0110 2
b0101 6
b0110 8
b00010 :
1<
0>
1?
1@
1C
b0101 O
0R
0U
1V
1Y
b0110 b
0c
1e
b0101 f
#341000
#345000
0#
0(
0-
0e
#350000
1#
1(
b001 *
1-
1e
#355000
0#
0(
0-
0e
#360000
1#
1(
b010 *
1-
1e
#365000
0#
0(
0-
0e
#370000
1#
1(
b011 *
1-
1e
#375000
0#
0(
0-
0e
#380000
1#
1%
1&
1(
1)
b100 *
1+
1-
1c
1e
#385000
0#
0(
0-
0e
#390000
1#
b0110 $
0%
0&
1(
0)
b000 *
0+
1-
b0110 .
b0111 0
b0110 1
b0111 2
b0110 6
b0111 8
b00000 :
0<
1>
0?
0@
1A
1C
0D
0E
1H
0I
0J
0M
b0110 O
1R
1U
1V
1Y
1Z
1]
0^
0a
b0111 b
0c
1e
b0110 f
#391000
#395000
0#
0(
0-
0e
#400000
1#
1(
b001 *
1-
1e
#405000
0#
0(
0-
0e
#410000
1#
1(
b010 *
1-
1e
#415000
0#
0(
0-
0e
#420000
1#
1(
b011 *
1-
1e
#425000
0#
0(
0-
0e
#430000
1#
1%
1&
1(
1)
b100 *
1+
1-
1c
1e
#435000
0#
0(
0-
0e
#440000
1#
b0111 $
0%
0&
1(
0)
b000 *
0+
1-
b0111 .
b1000 0
b0111 1
b1000 2
b0111 6
b1000 8
b01110 :
1<
0>
1?
1@
0C
1D
1E
0H
1I
1J
1M
b0111 O
0R
0U
0V
0Y
0Z
0]
1^
1a
b1000 b
0c
1e
b0111 f
#441000
#445000
0#
0(
0-
0e
#450000
1#
1(
b001 *
1-
1e
#455000
0#
0(
0-
0e
#460000
1#
1(
b010 *
1-
1e
#465000
0#
0(
0-
0e
#470000
1#
1(
b011 *
1-
1e
#475000
0#
0(
0-
0e
#480000
1#
1%
1&
1(
1)
b100 *
1+
1-
1c
1e
#485000
0#
0(
0-
0e
#490000
1#
b1000 $
0%
0&
1(
0)
b000 *
0+
1-
b1000 .
b1001 0
b1000 1
b1001 2
04
b1000 6
b1001 8
09
b00000 :
0<
1>
0?
0@
0A
0C
0D
0E
0F
0H
0I
0J
1K
1M
0N
b1000 O
1R
1U
0V
0Y
0Z
0]
1^
1a
b1001 b
0c
1e
b1000 f
#491000
#495000
0#
0(
0-
0e
#500000
1#
1(
b001 *
1-
1e
#505000
0#
0(
0-
0e
#510000
1#
1(
b010 *
1-
1e
#515000
0#
0(
0-
0e
#520000
1#
1(
b011 *
1-
1e
#525000
0#
0(
0-
0e
#530000
1#
1%
1&
1(
1)
b100 *
1+
1-
1c
1e
#535000
0#
0(
0-
0e
#540000
1#
b1001 $
0%
0&
1(
0)
b000 *
0+
1-
b1001 .
0/
b0000 0
b1001 1
b1010 2
13
b1001 6
b1010 8
b00010 :
1<
0>
1?
1@
1C
b1001 O
1Q
0R
1T
0U
1V
1X
1\
1`
0a
b0000 b
0c
1e
b1001 f
#541000
#545000
0#
0(
0-
0e
#550000
1#
1(
b001 *
1-
1e
#555000
0#
0(
0-
0e
#560000
1#
1(
b010 *
1-
1e
#565000
0#
0(
0-
0e
#570000
1#
1(
b011 *
1-
1e
#575000
0#
0(
0-
0e
#580000
1#
1%
1&
1(
1)
b100 *
1+
1-
1/
1c
1e
#585000
0#
0(
0-
0e
#590000
1#
b0000 $
0%
0&
1(
0)
b000 *
0+
1-
b0000 .
0/
b0001 0
b0000 1
b0001 2
03
b0000 6
b0001 8
b00000 :
0<
1>
0?
0@
0C
0K
0M
b0000 O
0Q
1R
0T
1U
0V
0X
0Y
0\
0^
0`
b0001 b
0c
1e
b0000 f
#591000
#595000
0#
0(
0-
0e
#600000
1#
1(
b001 *
1-
1e
#605000
0#
0(
0-
0e
#610000
1#
1(
b010 *
1-
1e
#615000
0#
0(
0-
0e
#620000
1#
1(
b011 *
1-
1e
#625000
0#
0(
0-
0e
#630000
1#
1%
1&
1(
1)
b100 *
1+
1-
1c
1e
#635000
0#
0(
0-
0e
#640000
1#
b0001 $
0%
0&
1(
0)
b000 *
0+
1-
b0001 .
b0010 0
b0001 1
b0010 2
b0001 6
b0010 8
b00010 :
1<
0>
1?
1@
1C
b0001 O
0R
0U
1V
1Y
b0010 b
0c
1e
b0001 f
#641000
#645000
0#
0(
0-
0e
#650000
1#
1(
b001 *
1-
1e
#655000
0#
0(
0-
0e
#660000
1#
1(
b010 *
1-
1e
#665000
0#
0(
0-
0e
#670000
1#
1(
b011 *
1-
1e
#675000
0#
0(
0-
0e
#680000
1#
1%
1&
1(
1)
b100 *
1+
1-
1c
1e
#685000
0#
0(
0-
0e
#690000
1#
b0010 $
0%
0&
1(
0)
b000 *
0+
1-
b0010 .
b0011 0
b0010 1
b0011 2
b0010 6
b0011 8
b00000 :
0<
1>
0?
0@
1A
1C
0D
0E
0H
b0010 O
1R
1U
1V
1Y
0Z
0]
b0011 b
0c
1e
b0010 f
#691000
0!
#695000
0#
0(
0-
0e
#700000
1#
1(
b001 *
1-
1e
#705000
0#
0(
0-
0e
#710000
1#
1(
b010 *
1-
1e
#715000
0#
0(
0-
0e
#720000
1#
1(
b011 *
1-
1e
#725000
0#
0(
0-
0e
#730000
1#
1%
1(
1)
b100 *
1-
1e
#735000
0#
0(
0-
0e
#740000
1#
0%
1(
0)
b000 *
1-
1e
#745000
0#
0(
0-
0e
#750000
1#
1(
b001 *
1-
1e
#755000
0#
0(
0-
0e
#760000
1#
1(
b010 *
1-
1e
#765000
0#
0(
0-
0e
#770000
1#
1(
b011 *
1-
1e
#775000
0#
0(
0-
0e
#780000
1#
1%
1(
1)
b100 *
1-
1e
#785000
0#
0(
0-
0e
#790000
1#
0%
1(
0)
b000 *
1-
1e
#791000
1!
#795000
0#
0(
0-
0e
#800000
1#
1(
b001 *
1-
1e
#805000
0#
0(
0-
0e
#810000
1#
1(
b010 *
1-
1e
#815000
0#
0(
0-
0e
#820000
1#
1(
b011 *
1-
1e
#825000
0#
0(
0-
0e
#830000
1#
1%
1&
1(
1)
b100 *
1+
1-
1c
1e
#835000
0#
0(
0-
0e
#840000
1#
b0011 $
0%
0&
1(
0)
b000 *
0+
1-
b0011 .
b0100 0
b0011 1
b0100 2
b0011 6
b0100 8
b00110 :
1<
0>
1?
1@
0C
1D
1E
1H
b0011 O
0R
0U
0V
0Y
1Z
1]
b0100 b
0c
1e
b0011 f
#841000
#845000
0#
0(
0-
0e
#850000
1#
1(
b001 *
1-
1e
#855000
0#
0(
0-
0e
#860000
1#
1(
b010 *
1-
1e
#865000
0#
0(
0-
0e
#870000
1#
1(
b011 *
1-
1e
#875000
0#
0(
0-
0e
#880000
1#
1%
1&
1(
1)
b100 *
1+
1-
1c
1e
#885000
0#
0(
0-
0e
#890000
1#
b0100 $
0%
0&
1(
0)
b000 *
0+
1-
b0100 .
b0101 0
b0100 1
b0101 2
b0100 6
b0101 8
b00000 :
0<
1>
0?
0@
0A
0C
0D
0E
1F
1H
0I
0J
0M
b0100 O
1R
1U
0V
0Y
1Z
1]
0^
0a
b0101 b
0c
1e
b0100 f
#895000
0#
0(
0-
0e
#900000
1#
1(
b001 *
1-
1e
#905000
0#
0(
0-
0e
#910000
1#
1(
b010 *
1-
1e
#915000
0#
0(
0-
0e
#920000
1#
1(
b011 *
1-
1e
#925000
0#
0(
0-
0e
#930000
1#
1%
1&
1(
1)
b100 *
1+
1-
1c
1e
#935000
0#
0(
0-
0e
#940000
1#
b0101 $
0%
0&
1(
0)
b000 *
0+
1-
b0101 .
b0110 0
b0101 1
b0110 2
b0101 6
b0110 8
b00010 :
1<
0>
1?
1@
1C
b0101 O
0R
0U
1V
1Y
b0110 b
0c
1e
b0101 f
