Guia_TP/CLP_CESE/CLP_CESE.srcs/sources_1/new/ffd.vhd
----------------------------------------------------------------------------------
-- Company: 
-- Engineer: 
-- 
-- Create Date: 27.08.2026 20:49:25
-- Design Name: 
-- Module Name: ffd - Behavioral
-- Project Name: 
-- Target Devices: 
-- Tool Versions: 
-- Description: Flip-flop D con enable y reset sincrono activos en alto.
-- 
-- Dependencies: 
-- 
-- Revision:
-- Revision 0.01 - File Created
-- Additional Comments:
-- 
----------------------------------------------------------------------------------


library IEEE;
use IEEE.STD_LOGIC_1164.ALL;

-- Uncomment the following library declaration if using
-- arithmetic functions with Signed or Unsigned values
--use IEEE.NUMERIC_STD.ALL;

-- Uncomment the following library declaration if instantiating
-- any Xilinx leaf cells in this code.
--library UNISIM;
--use UNISIM.VComponents.all;

entity ffd is
    Port ( d : in STD_LOGIC;
           ena : in STD_LOGIC;
           rst : in STD_LOGIC;
           clk : in STD_LOGIC;
           q : out STD_LOGIC);
end ffd;

architecture Behavioral of ffd is

begin
    
    process(clk)
    begin
        if rising_edge(clk) then
            if rst = '1' then
                q<='0';    
            else
                if ena = '1' then
                    q<=d;
                end if;
            end if;
        end if;
    end process;

end Behavioral;

Guia_TP/CLP_CESE/CLP_CESE.srcs/sources_1/new/celda_unitaria_contador_binario.vhd
----------------------------------------------------------------------------------
-- Company: 
-- Engineer: 
-- 
-- Create Date: 27.08.2026 22:24:13
-- Design Name: 
-- Module Name: celda_unitaria_contador_binario - Behavioral
-- Project Name: 
-- Target Devices: 
-- Tool Versions: 
-- Description: Celda de 1 bit para construir contadores binarios estructurales.
-- 
-- Dependencies: 
-- 
-- Revision:
-- Revision 0.01 - File Created
-- Additional Comments:
-- 
----------------------------------------------------------------------------------


library IEEE;
use IEEE.STD_LOGIC_1164.ALL;

-- Uncomment the following library declaration if using
-- arithmetic functions with Signed or Unsigned values
--use IEEE.NUMERIC_STD.ALL;

-- Uncomment the following library declaration if instantiating
-- any Xilinx leaf cells in this code.
--library UNISIM;
--use UNISIM.VComponents.all;

entity celda_unitaria_contador_binario is
    Port (
        ena_in  : in  STD_LOGIC;
        rst     : in  STD_LOGIC;
        clk     : in  STD_LOGIC;
        q       : out STD_LOGIC;
        ena_out : out STD_LOGIC
    );
end celda_unitaria_contador_binario;

architecture Behavioral of celda_unitaria_contador_binario is

    signal d_aux : STD_LOGIC;
    signal q_aux : STD_LOGIC;

begin

    d_aux   <= q_aux xor ena_in;
    ena_out <= q_aux and ena_in;
    q       <= q_aux;

    ffd_instance : entity work.ffd
        port map (
            d   => d_aux,
            ena => '1',
            rst => rst,
            clk => clk,
            q   => q_aux
        );

end Behavioral;

Guia_TP/CLP_CESE/CLP_CESE.srcs/sources_1/new/contador_binario_4_bits.vhd
----------------------------------------------------------------------------------
-- Company: 
-- Engineer: 
-- 
-- Create Date: 27.08.2026 22:24:12
-- Design Name: 
-- Module Name: contador_binario_4_bits - Behavioral
-- Project Name: 
-- Target Devices: 
-- Tool Versions: 
-- Description: Contador binario estructural de 4 bits con reset y enable.
-- 
-- Dependencies: 
-- 
-- Revision:
-- Revision 0.01 - File Created
-- Additional Comments:
-- 
----------------------------------------------------------------------------------


library IEEE;
use IEEE.STD_LOGIC_1164.ALL;

-- Uncomment the following library declaration if using
-- arithmetic functions with Signed or Unsigned values
--use IEEE.NUMERIC_STD.ALL;

-- Uncomment the following library declaration if instantiating
-- any Xilinx leaf cells in this code.
--library UNISIM;
--use UNISIM.VComponents.all;

entity contador_binario_4_bits is
    Port (
        ena : in  STD_LOGIC;
        rst : in  STD_LOGIC;
        clk : in  STD_LOGIC;
        q   : out STD_LOGIC_VECTOR(3 downto 0)
    );
end contador_binario_4_bits;

architecture Behavioral of contador_binario_4_bits is

    signal ena_aux : STD_LOGIC_VECTOR(4 downto 0);

begin

    ena_aux(0) <= ena;

    celdas : for i in 0 to 3 generate
        celda_instance : entity work.celda_unitaria_contador_binario
            port map (
                ena_in  => ena_aux(i),
                rst     => rst,
                clk     => clk,
                q       => q(i),
                ena_out => ena_aux(i + 1)
            );
    end generate celdas;

end Behavioral;

Guia_TP/cocotb/waveforms/contador_binario_4_bits.vcd
$date
  Sun Aug 30 19:25:36 2026
$end
$version
  GHDL v0
$end
$timescale
  1 ps
$end
$scope module standard $end
$upscope $end
$scope module textio $end
$upscope $end
$scope module std_logic_1164 $end
$upscope $end
$scope module contador_binario_4_bits $end
$var reg 1 ! ena $end
$var reg 1 " rst $end
$var reg 1 # clk $end
$var reg 4 $ q[3:0] $end
$var reg 5 % ena_aux[4:0] $end
$scope module celdas(0) $end
$scope module celda_instance $end
$var reg 1 & ena_in $end
$var reg 1 ' rst $end
$var reg 1 ( clk $end
$var reg 1 ) q $end
$var reg 1 * ena_out $end
$var reg 1 + d_aux $end
$var reg 1 , q_aux $end
$scope module ffd_instance $end
$var reg 1 - d $end
$var reg 1 . ena $end
$var reg 1 / rst $end
$var reg 1 0 clk $end
$var reg 1 1 q $end
$upscope $end
$upscope $end
$upscope $end
$scope module celdas(1) $end
$scope module celda_instance $end
$var reg 1 2 ena_in $end
$var reg 1 3 rst $end
$var reg 1 4 clk $end
$var reg 1 5 q $end
$var reg 1 6 ena_out $end
$var reg 1 7 d_aux $end
$var reg 1 8 q_aux $end
$scope module ffd_instance $end
$var reg 1 9 d $end
$var reg 1 : ena $end
$var reg 1 ; rst $end
$var reg 1 < clk $end
$var reg 1 = q $end
$upscope $end
$upscope $end
$upscope $end
$scope module celdas(2) $end
$scope module celda_instance $end
$var reg 1 > ena_in $end
$var reg 1 ? rst $end
$var reg 1 @ clk $end
$var reg 1 A q $end
$var reg 1 B ena_out $end
$var reg 1 C d_aux $end
$var reg 1 D q_aux $end
$scope module ffd_instance $end
$var reg 1 E d $end
$var reg 1 F ena $end
$var reg 1 G rst $end
$var reg 1 H clk $end
$var reg 1 I q $end
$upscope $end
$upscope $end
$upscope $end
$scope module celdas(3) $end
$scope module celda_instance $end
$var reg 1 J ena_in $end
$var reg 1 K rst $end
$var reg 1 L clk $end
$var reg 1 M q $end
$var reg 1 N ena_out $end
$var reg 1 O d_aux $end
$var reg 1 P q_aux $end
$scope module ffd_instance $end
$var reg 1 Q d $end
$var reg 1 R ena $end
$var reg 1 S rst $end
$var reg 1 T clk $end
$var reg 1 U q $end
$upscope $end
$upscope $end
$upscope $end
$upscope $end
$enddefinitions $end
#0
0!
1"
1#
bUUUU $
b00000 %
0&
1'
1(
U)
0*
U+
U,
U-
1.
1/
10
U1
02
13
14
U5
06
U7
U8
U9
1:
1;
1<
U=
0>
1?
1@
UA
0B
UC
UD
UE
1F
1G
1H
UI
0J
1K
1L
UM
0N
UO
UP
UQ
1R
1S
1T
UU
#5000
0#
0(
00
04
0<
0@
0H
0L
0T
#10000
1#
b0000 $
1(
0)
0+
0,
0-
10
01
14
05
07
08
09
1<
0=
1@
0A
0C
0D
0E
1H
0I
1L
0M
0O
0P
0Q
1T
0U
#15000
0#
0(
00
04
0<
0@
0H
0L
0T
#20000
1#
1(
10
14
1<
1@
1H
1L
1T
#25000
0#
0(
00
04
0<
0@
0H
0L
0T
#30000
1#
1(
10
14
1<
1@
1H
1L
1T
#35000
0#
0(
00
04
0<
0@
0H
0L
0T
#40000
1#
1(
10
14
1<
1@
1H
1L
1T
#41000
0"
0'
0/
03
0;
0?
0G
0K
0S
#42000
#45000
0#
0(
00
04
0<
0@
0H
0L
0T
#50000
1#
1(
10
14
1<
1@
1H
1L
1T
#55000
0#
0(
00
04
0<
0@
0H
0L
0T
#60000
1#
1(
10
14
1<
1@
1H
1L
1T
#61000
1!
b00001 %
1&
1+
1-
#65000
0#
0(
00
04
0<
0@
0H
0L
0T
#70000
1#
b0001 $
b00011 %
1(
1)
1*
0+
1,
0-
10
11
12
14
17
19
1<
1@
1H
1L
1T
#71000
#75000
0#
0(
00
04
0<
0@
0H
0L
0T
#80000
1#
b0010 $
b00001 %
1(
0)
0*
1+
0,
1-
10
01
02
14
15
06
17
18
19
1<
1=
0>
1@
0C
0E
1H
1L
1T
#81000
#85000
0#
0(
00
04
0<
0@
0H
0L
0T
#90000
1#
b0011 $
b00111 %
1(
1)
1*
0+
1,
0-
10
11
12
14
16
07
09
1<
1>
1@
1C
1E
1H
1L
1T
#91000
#95000
0#
0(
00
04
0<
0@
0H
0L
0T
#100000
1#
b0100 $
b00001 %
1(
0)
0*
1+
0,
1-
10
01
02
14
05
06
07
08
09
1<
0=
0>
1@
1A
0B
1C
1D
1E
1H
1I
0J
1L
0O
0Q
1T
#101000
#105000
0#
0(
00
04
0<
0@
0H
0L
0T
#110000
1#
b0101 $
b00011 %
1(
1)
1*
0+
1,
0-
10
11
12
14
17
19
1<
1@
1H
1L
1T
#111000
#115000
0#
0(
00
04
0<
0@
0H
0L
0T
#120000
1#
b0110 $
b00001 %
1(
0)
0*
1+
0,
1-
10
01
02
14
15
06
17
18
19
1<
1=
0>
1@
0B
1C
1E
1H
0J
1L
0O
0Q
1T
#121000
#125000
0#
0(
00
04
0<
0@
0H
0L
0T
#130000
1#
b0111 $
b01111 %
1(
1)
1*
0+
1,
0-
10
11
12
14
16
07
09
1<
1>
1@
1B
0C
0E
1H
1J
1L
1O
1Q
1T
#131000
#135000
0#
0(
00
04
0<
0@
0H
0L
0T
#140000
1#
b1000 $
b00001 %
1(
0)
0*
1+
0,
1-
10
01
02
14
05
06
07
08
09
1<
0=
0>
1@
0A
0B
0C
0D
0E
1H
0I
0J
1L
1M
0N
1O
1P
1Q
1T
1U
#141000
#145000
0#
0(
00
04
0<
0@
0H
0L
0T
#150000
1#
b1001 $
b00011 %
1(
1)
1*
0+
1,
0-
10
11
12
14
17
19
1<
1@
1H
1L
1T
#151000
#155000
0#
0(
00
04
0<
0@
0H
0L
0T
#160000
1#
b1010 $
b00001 %
1(
0)
0*
1+
0,
1-
10
01
02
14
15
06
17
18
19
1<
1=
0>
1@
0C
0E
1H
1L
1T
#161000
#165000
0#
0(
00
04
0<
0@
0H
0L
0T
#170000
1#
b1011 $
b00111 %
1(
1)
1*
0+
1,
0-
10
11
12
14
16
07
09
1<
1>
1@
1C
1E
1H
1L
1T
#171000
#175000
0#
0(
00
04
0<
0@
0H
0L
0T
#180000
1#
b1100 $
b00001 %
1(
0)
0*
1+
0,
1-
10
01
02
14
05
06
07
08
09
1<
0=
0>
1@
1A
0B
1C
1D
1E
1H
1I
0J
1L
0N
1O
1Q
1T
#181000
#185000
0#
0(
00
04
0<
0@
0H
0L
0T
#190000
1#
b1101 $
b00011 %
1(
1)
1*
0+
1,
0-
10
11
12
14
17
19
1<
1@
1H
1L
1T
#191000
#195000
0#
0(
00
04
0<
0@
0H
0L
0T
#200000
1#
b1110 $
b00001 %
1(
0)
0*
1+
0,
1-
10
01
02
14
15
06
17
18
19
1<
1=
0>
1@
0B
1C
1E
1H
0J
1L
0N
1O
1Q
1T
#201000
#205000
0#
0(
00
04
0<
0@
0H
0L
0T
#210000
1#
b1111 $
b11111 %
1(
1)
1*
0+
1,
0-
10
11
12
14
16
07
09
1<
1>
1@
1B
0C
0E
1H
1J
1L
1N
0O
0Q
1T
#211000
#215000
0#
0(
00
04
0<
0@
0H
0L
0T
#220000
1#
b0000 $
b00001 %
1(
0)
0*
1+
0,
1-
10
01
02
14
05
06
07
08
09
1<
0=
0>
1@
0A
0B
0C
0D
0E
1H
0I
0J
1L
0M
0N
0O
0P
0Q
1T
0U
#221000
0!
b00000 %
0&
0+
0-
#225000
0#
0(
00
04
0<
0@
0H
0L
0T
#230000
1#
1(
10
14
1<
1@
1H
1L
1T
#231000
1!
b00001 %
1&
1+
1-
#235000
0#
0(
00
04
0<
0@
0H
0L
0T
#240000
1#
b0001 $
b00011 %
1(
1)
1*
0+
1,
0-
10
11
12
14
17
19
1<
1@
1H
1L
1T
#241000
#245000
0#
0(
00
04
0<
0@
0H
0L
0T
#250000
1#
b0010 $
b00001 %
1(
0)
0*
1+
0,
1-
10
01
02
14
15
06
17
18
19
1<
1=
0>
1@
0C
0E
1H
1L
1T
#255000
0#
0(
00
04
0<
0@
0H
0L
0T
#260000
1#
b0011 $
b00111 %
1(
1)
1*
0+
1,
0-
10
11
12
14
16
07
09
1<
1>
1@
1C
1E
1H
1L
1T
#265000
0#
0(
00
04
0<
0@
0H
0L
0T
#270000
1#
b0100 $
b00001 %
1(
0)
0*
1+
0,
1-
10
01
02
14
05
06
07
08
09
1<
0=
0>
1@
1A
0B
1C
1D
1E
1H
1I
0J
1L
0O
0Q
1T
#275000
0#
0(
00
04
0<
0@
0H
0L
0T
#280000
1#
b0101 $
b00011 %
1(
1)
1*
0+
1,
0-
10
11
12
14
17
19
1<
1@
1H
1L
1T
#285000
0#
0(
00
04
0<
0@
0H
0L
0T
#290000
1#
b0110 $
b00001 %
1(
0)
0*
1+
0,
1-
10
01
02
14
15
06
17
18
19
1<
1=
0>
1@
0B
1C
1E
1H
0J
1L
0O
0Q
1T
#295000
0#
0(
00
04
0<
0@
0H
0L
0T
#300000
1#
b0111 $
b01111 %
1(
1)
1*
0+
1,
0-
10
11
12
14
16
07
09
1<
1>
1@
1B
0C
0E
1H
1J
1L
1O
1Q
1T
#305000
0#
0(
00
04
0<
0@
0H
0L
0T
#310000
1#
b1000 $
b00001 %
1(
0)
0*
1+
0,
1-
10
01
02
14
05
06
07
08
09
1<
0=
0>
1@
0A
0B
0C
0D
0E
1H
0I
0J
1L
1M
0N
1O
1P
1Q
1T
1U
#315000
0#
0(
00
04
0<
0@
0H
0L
0T
#320000
1#
b1001 $
b00011 %
1(
1)
1*
0+
1,
0-
10
11
12
14
17
19
1<
1@
1H
1L
1T
#325000
0#
0(
00
04
0<
0@
0H
0L
0T
#330000
1#
b1010 $
b00001 %
1(
0)
0*
1+
0,
1-
10
01
02
14
15
06
17
18
19
1<
1=
0>
1@
0C
0E
1H
1L
1T
#335000
0#
0(
00
04
0<
0@
0H
0L
0T
#340000
1#
b1011 $
b00111 %
1(
1)
1*
0+
1,
0-
10
11
12
14
16
07
09
1<
1>
1@
1C
1E
1H
1L
1T
