Guia_TP/CLP_CESE/CLP_CESE.srcs/sources_1/new/ffd.vhd
----------------------------------------------------------------------------------
-- Company: 
-- Engineer: 
-- 
-- Create Date: 27.08.2026 20:49:25
-- Design Name: 
-- Module Name: ffd - Behavioral
-- Project Name: 
-- Target Devices: 
-- Tool Versions: 
-- Description: Flip-flop D con enable y reset sincrono activos en alto.
-- 
-- Dependencies: 
-- 
-- Revision:
-- Revision 0.01 - File Created
-- Additional Comments:
-- 
----------------------------------------------------------------------------------


library IEEE;
use IEEE.STD_LOGIC_1164.ALL;

-- Uncomment the following library declaration if using
-- arithmetic functions with Signed or Unsigned values
--use IEEE.NUMERIC_STD.ALL;

-- Uncomment the following library declaration if instantiating
-- any Xilinx leaf cells in this code.
--library UNISIM;
--use UNISIM.VComponents.all;

entity ffd is
    Port ( d : in STD_LOGIC;
           ena : in STD_LOGIC;
           rst : in STD_LOGIC;
           clk : in STD_LOGIC;
           q : out STD_LOGIC);
end ffd;

architecture Behavioral of ffd is

begin
    
    process(clk)
    begin
        if rising_edge(clk) then
            if rst = '1' then
                q<='0';    
            else
                if ena = '1' then
                    q<=d;
                end if;
            end if;
        end if;
    end process;

end Behavioral;

Guia_TP/cocotb/waveforms/ffd.vcd
$date
  Sun Aug 30 19:26:02 2026
$end
$version
  GHDL v0
$end
$timescale
  1 ps
$end
$scope module standard $end
$upscope $end
$scope module textio $end
$upscope $end
$scope module std_logic_1164 $end
$upscope $end
$scope module ffd $end
$var reg 1 ! d $end
$var reg 1 " ena $end
$var reg 1 # rst $end
$var reg 1 $ clk $end
$var reg 1 % q $end
$upscope $end
$enddefinitions $end
#0
0!
0"
1#
1$
U%
#5000
0$
#10000
1$
0%
#15000
0$
#20000
1$
#25000
0$
#30000
1$
#35000
0$
#40000
1$
#41000
0#
#42000
1!
1"
#45000
0$
#50000
1$
1%
#51000
#55000
0$
#60000
1$
#65000
0$
#70000
1$
#75000
0$
#80000
1$
#85000
0$
#90000
1$
#95000
0$
#100000
1$
#105000
0$
#110000
1$
#115000
0$
#120000
1$
#125000
0$
#130000
1$
#135000
0$
#140000
1$
#145000
0$
#150000
1$
#151000
0!
0"
#155000
0$
#160000
1$
#161000
1"
#165000
0$
#170000
1$
0%
#171000
1!
#175000
0$
#180000
1$
1%
