Guia_TP/CLP_CESE/CLP_CESE.srcs/sources_1/new/mux_2_a_1.vhd
----------------------------------------------------------------------------------
-- Company: 
-- Engineer: 
-- 
-- Create Date: 27.08.2026 20:36:34
-- Design Name: 
-- Module Name: mux_2_a_1 - Behavioral
-- Project Name: 
-- Target Devices: 
-- Tool Versions: 
-- Description: Multiplexor combinacional de dos entradas de 1 bit.
-- 
-- Dependencies: 
-- 
-- Revision:
-- Revision 0.01 - File Created
-- Additional Comments:
-- 
----------------------------------------------------------------------------------


library IEEE;
use IEEE.STD_LOGIC_1164.ALL;

-- Uncomment the following library declaration if using
-- arithmetic functions with Signed or Unsigned values
--use IEEE.NUMERIC_STD.ALL;

-- Uncomment the following library declaration if instantiating
-- any Xilinx leaf cells in this code.
--library UNISIM;
--use UNISIM.VComponents.all;

entity mux_2_a_1 is
    Port (  a : in STD_LOGIC;
            b : in STD_LOGIC;
           sel: in STD_LOGIC;
           mux: out STD_LOGIC);
end mux_2_a_1;

architecture Behavioral of mux_2_a_1 is

begin
    mux<= a when sel='0' else b;
end Behavioral;

Guia_TP/cocotb/waveforms/mux_2_a_1.vcd
$date
  Sun Aug 30 19:26:08 2026
$end
$version
  GHDL v0
$end
$timescale
  1 ps
$end
$scope module standard $end
$upscope $end
$scope module textio $end
$upscope $end
$scope module std_logic_1164 $end
$upscope $end
$scope module mux_2_a_1 $end
$var reg 1 ! a $end
$var reg 1 " b $end
$var reg 1 # sel $end
$var reg 1 $ mux $end
$upscope $end
$enddefinitions $end
#0
0!
0"
0#
0$
#10000
1"
#20000
1!
0"
1$
#30000
1"
#40000
0!
0"
1#
0$
#50000
1"
1$
#60000
1!
0"
0$
#70000
1"
1$
