Guia_TP/CLP_CESE/CLP_CESE.srcs/sources_1/new/reg_desp_comportamiento.vhd
----------------------------------------------------------------------------------
-- Company: 
-- Engineer: 
-- 
-- Create Date: 27.08.2026 21:21:13
-- Design Name: 
-- Module Name: reg_desp_comportamiento - Behavioral
-- Project Name: 
-- Target Devices: 
-- Tool Versions: 
-- Description: Registro de desplazamiento serie de 4 bits por comportamiento.
-- 
-- Dependencies: 
-- 
-- Revision:
-- Revision 0.01 - File Created
-- Additional Comments:
-- 
----------------------------------------------------------------------------------


library IEEE;
use IEEE.STD_LOGIC_1164.ALL;

-- Uncomment the following library declaration if using
-- arithmetic functions with Signed or Unsigned values
--use IEEE.NUMERIC_STD.ALL;

-- Uncomment the following library declaration if instantiating
-- any Xilinx leaf cells in this code.
--library UNISIM;
--use UNISIM.VComponents.all;

entity reg_desp_comportamiento is
    Port ( E : in STD_LOGIC;
           S : out STD_LOGIC;
           rst : in STD_LOGIC;
           clk : in STD_LOGIC);
end reg_desp_comportamiento;

architecture Behavioral of reg_desp_comportamiento is
    signal q: STD_LOGIC_VECTOR(4-1 downto 0);
begin
    
    process(clk)
    begin
        if rising_edge(clk) then
            if rst = '1' then
                q<=(others=>'0');
            else
                q<= E & q(4-1 downto 1);
            end if;                
        end if;
    end process;
    S <= q(0);    

end Behavioral;

Guia_TP/cocotb/waveforms/reg_desp_comportamiento.vcd
$date
  Sun Aug 30 19:26:15 2026
$end
$version
  GHDL v0
$end
$timescale
  1 ps
$end
$scope module standard $end
$upscope $end
$scope module textio $end
$upscope $end
$scope module std_logic_1164 $end
$upscope $end
$scope module reg_desp_comportamiento $end
$var reg 1 ! e $end
$var reg 1 " s $end
$var reg 1 # rst $end
$var reg 1 $ clk $end
$var reg 4 % q[3:0] $end
$upscope $end
$enddefinitions $end
#0
0!
U"
1#
1$
bUUUU %
#5000
0$
#10000
0"
1$
b0000 %
#15000
0$
#20000
1$
#25000
0$
#30000
1$
#35000
0$
#40000
1$
#41000
0#
#42000
1!
#45000
0$
#50000
1$
b1000 %
#51000
0!
#55000
0$
#60000
1$
b0100 %
#61000
1!
#65000
0$
#70000
1$
b1010 %
#71000
#75000
0$
#80000
1"
1$
b1101 %
#81000
0!
#85000
0$
#90000
0"
1$
b0110 %
#91000
#95000
0$
#100000
1"
1$
b0011 %
#101000
#105000
0$
#110000
1$
b0001 %
#111000
#115000
0$
#120000
0"
1$
b0000 %
