Guia_TP/CLP_CESE/CLP_CESE.srcs/sources_1/new/ffd.vhd
----------------------------------------------------------------------------------
-- Company: 
-- Engineer: 
-- 
-- Create Date: 27.08.2026 20:49:25
-- Design Name: 
-- Module Name: ffd - Behavioral
-- Project Name: 
-- Target Devices: 
-- Tool Versions: 
-- Description: Flip-flop D con enable y reset sincrono activos en alto.
-- 
-- Dependencies: 
-- 
-- Revision:
-- Revision 0.01 - File Created
-- Additional Comments:
-- 
----------------------------------------------------------------------------------


library IEEE;
use IEEE.STD_LOGIC_1164.ALL;

-- Uncomment the following library declaration if using
-- arithmetic functions with Signed or Unsigned values
--use IEEE.NUMERIC_STD.ALL;

-- Uncomment the following library declaration if instantiating
-- any Xilinx leaf cells in this code.
--library UNISIM;
--use UNISIM.VComponents.all;

entity ffd is
    Port ( d : in STD_LOGIC;
           ena : in STD_LOGIC;
           rst : in STD_LOGIC;
           clk : in STD_LOGIC;
           q : out STD_LOGIC);
end ffd;

architecture Behavioral of ffd is

begin
    
    process(clk)
    begin
        if rising_edge(clk) then
            if rst = '1' then
                q<='0';    
            else
                if ena = '1' then
                    q<=d;
                end if;
            end if;
        end if;
    end process;

end Behavioral;

Guia_TP/CLP_CESE/CLP_CESE.srcs/sources_1/new/reg_desp_estructural.vhd
----------------------------------------------------------------------------------
-- Company: 
-- Engineer: 
-- 
-- Create Date: 27.08.2026 20:58:49
-- Design Name: 
-- Module Name: reg_desp_estructural - Behavioral
-- Project Name: 
-- Target Devices: 
-- Tool Versions: 
-- Description: Registro de desplazamiento serie de 4 bits formado por FFD.
-- 
-- Dependencies: 
-- 
-- Revision:
-- Revision 0.01 - File Created
-- Additional Comments:
-- 
----------------------------------------------------------------------------------


library IEEE;
use IEEE.STD_LOGIC_1164.ALL;

-- Uncomment the following library declaration if using
-- arithmetic functions with Signed or Unsigned values
--use IEEE.NUMERIC_STD.ALL;

-- Uncomment the following library declaration if instantiating
-- any Xilinx leaf cells in this code.
--library UNISIM;
--use UNISIM.VComponents.all;

entity reg_desp_estructural is
    Port ( E : in STD_LOGIC;
           S : out STD_LOGIC;
           rst : in STD_LOGIC;
           clk : in STD_LOGIC);
end reg_desp_estructural;

architecture Behavioral of reg_desp_estructural is

    signal reg_aux : STD_LOGIC_VECTOR(4 downto 0);

begin

    reg_aux(0) <= E;
    S <= reg_aux(4);

    registro : for i in 0 to 3 generate
        ffd_instance : entity work.ffd
            port map (
                d   => reg_aux(i),
                ena => '1',
                rst => rst,
                clk => clk,
                q   => reg_aux(i + 1)
            );
    end generate registro;

end Behavioral;

Guia_TP/cocotb/waveforms/reg_desp_estructural.vcd
$date
  Sun Aug 30 19:26:21 2026
$end
$version
  GHDL v0
$end
$timescale
  1 ps
$end
$scope module standard $end
$upscope $end
$scope module textio $end
$upscope $end
$scope module std_logic_1164 $end
$upscope $end
$scope module reg_desp_estructural $end
$var reg 1 ! e $end
$var reg 1 " s $end
$var reg 1 # rst $end
$var reg 1 $ clk $end
$var reg 5 % reg_aux[4:0] $end
$scope module registro(0) $end
$scope module ffd_instance $end
$var reg 1 & d $end
$var reg 1 ' ena $end
$var reg 1 ( rst $end
$var reg 1 ) clk $end
$var reg 1 * q $end
$upscope $end
$upscope $end
$scope module registro(1) $end
$scope module ffd_instance $end
$var reg 1 + d $end
$var reg 1 , ena $end
$var reg 1 - rst $end
$var reg 1 . clk $end
$var reg 1 / q $end
$upscope $end
$upscope $end
$scope module registro(2) $end
$scope module ffd_instance $end
$var reg 1 0 d $end
$var reg 1 1 ena $end
$var reg 1 2 rst $end
$var reg 1 3 clk $end
$var reg 1 4 q $end
$upscope $end
$upscope $end
$scope module registro(3) $end
$scope module ffd_instance $end
$var reg 1 5 d $end
$var reg 1 6 ena $end
$var reg 1 7 rst $end
$var reg 1 8 clk $end
$var reg 1 9 q $end
$upscope $end
$upscope $end
$upscope $end
$enddefinitions $end
#0
0!
U"
1#
1$
bUUUU0 %
0&
1'
1(
1)
U*
U+
1,
1-
1.
U/
U0
11
12
13
U4
U5
16
17
18
U9
#5000
0$
0)
0.
03
08
#10000
0"
1$
b00000 %
1)
0*
0+
1.
0/
00
13
04
05
18
09
#15000
0$
0)
0.
03
08
#20000
1$
1)
1.
13
18
#25000
0$
0)
0.
03
08
#30000
1$
1)
1.
13
18
#35000
0$
0)
0.
03
08
#40000
1$
1)
1.
13
18
#41000
0#
0(
0-
02
07
#42000
1!
b00001 %
1&
#45000
0$
0)
0.
03
08
#50000
1$
b00011 %
1)
1*
1+
1.
13
18
#51000
0!
b00010 %
0&
#55000
0$
0)
0.
03
08
#60000
1$
b00100 %
1)
0*
0+
1.
1/
10
13
18
#61000
1!
b00101 %
1&
#65000
0$
0)
0.
03
08
#70000
1$
b01011 %
1)
1*
1+
1.
0/
00
13
14
15
18
#71000
#75000
0$
0)
0.
03
08
#80000
1"
1$
b10111 %
1)
1.
1/
10
13
04
05
18
19
#81000
0!
b10110 %
0&
#85000
0$
0)
0.
03
08
#90000
0"
1$
b01100 %
1)
0*
0+
1.
13
14
15
18
09
#91000
#95000
0$
0)
0.
03
08
#100000
1"
1$
b11000 %
1)
1.
0/
00
13
18
19
#101000
#105000
0$
0)
0.
03
08
#110000
1$
b10000 %
1)
1.
13
04
05
18
#111000
#115000
0$
0)
0.
03
08
#120000
0"
1$
b00000 %
1)
1.
13
18
09
